Workbook

Sheet Instruções
A1: PLANILHA DE ANÁLISE FINANCEIRA – VPL, TIR E PAYBACK
A2: Viabilidade de projetos empreendedores – Projetos Empreendedores, Mackenzie
A4: PASSO A PASSO
A5: 1. Aba Fluxo de Caixa: preencha SÓ as células CINZAS (vendas, despesas e investimentos de cada período).
A6: 2. Período 0 = hoje, antes de começar a vender. Coloque ali o investimento inicial (equipamentos, reforma, abertura da empresa etc.).
A7: 3. Períodos 1 a 24 = meses (ou anos) de operação. Se o projeto durar menos, deixe os períodos restantes em branco.
A8: 4. Aba VPL e TIR: informe a taxa de desconto ANUAL e se os períodos são meses ou anos. A planilha converte a taxa sozinha.
A9: 5. Leia os resultados (VPL, TIR, payback) e a frase de decisão. Células AZUIS são automáticas e estão protegidas.
A11: LEGENDA DE CORES
A12: Cinza = você preenche | Azul = cálculo automático | Amarelo = resultado principal | Verde/vermelho = viável/inviável
A13: Passe o mouse sobre os títulos das colunas para ver a explicação de cada uma.
A15: GLOSSÁRIO
... A32: • Os valores que já vêm na planilha são apenas EXEMPLO. Substitua pelos dados do seu projeto.

Sheet Premissas Precept
A1: PREMISSAS DA PRECEPT – BASE DA FICHA DE LEVANTAMENTO FINANCEIRO
A2: Células CINZAS = premissas (podem ser alteradas para testar cenários). Células AZUIS = cálculo automático. Tudo aqui alimenta a aba Projeção Mensal, que alimenta a aba Fluxo de Caixa.
A4: 1. PREÇOS E RECEITA
A5: Precept Core – assinatura mensal (R$/mês) | B5: 1996 | C5: Preço único definido pelo grupo, com 5 licenças incluídas (1 master + 4 dependentes). Referência de mercado: ADVBOX R$ 220–1.800/mês (Big Offices a partir de R$ 5.000); Astrea R$ 209–1.249/mês (sites oficiais, out/2026).
A6: Licenças incluídas por assinatura | B6: 5 | C6: 1 acesso master + 4 dependentes.
A7: Licença extra (R$/mês) | B7: 300 | C7: Política de preço do grupo. Para simplificar, não entra na projeção: é receita adicional não contada (o modelo fica conservador).
A8: Ticket do Core usado na projeção (R$/mês) | B8: =B5 -> 1996 | C8: Igual ao preço da assinatura.
A9: Precept Sprint – planejamento de 7 dias (R$ por imersão) | B9: 9997 | C9: Preço definido pelo grupo: planejamento estratégico e tático em 7 dias imersivos. Recebido no mês da venda (Pix ou cartão).
A10: Precept Scale – implementação (R$ por projeto) | B10: 29997 | C10: Preço proposto: 3× o Sprint, equivalente a ~R$ 5 mil por mês de entrega, abaixo de consultorias de gestão para PMEs (R$ 8–15 mil/mês). Recebido no mês da venda (Pix ou cartão).
A11: Duração da implementação do Scale (meses) | B11: 6 | C11: Entrega em 6 meses, 1 pilar implementado por mês. O pagamento não depende da duração.
A12: Recebimento do Sprint e do Scale | B12: Mês da venda | C12: Valor cheio no mês da venda: Pix à vista ou cartão parcelado pelo cliente, com a operadora antecipando o valor para a Precept.
A14: 2. DESPESAS VARIÁVEIS
A15: Tokens de IA e nuvem por cliente Core ativo (R$/mês) | B15: 90 | C15: API Claude Sonnet 4.6: US$ 3 (entrada) e US$ 15 (saída) por milhão de tokens. ~3 mi de entrada + 0,5 mi de saída por cliente ≈ US$ 16,5 ≈ R$ 90 (câmbio ~R$ 5,50).
A16: Meio de pagamento – Pix, boleto e cartão (% da venda) | B16: 0.02 | C16: Asaas: Pix e boleto R$ 1,99 por cobrança; cartão à vista 2,99% + R$ 0,49; parcelado em 2 a 6x 3,49% + R$ 0,49, mais a antecipação (asaas.com/precos-e-taxas). Média ponderada ≈ 2%, supondo a maioria dos pagamentos via Pix ou boleto.
A17: Comissão de parceiros (% da receita de Sprint e Scale) | B17: 0.05 | C17: 10% para parceiros que indicam (contadores, associações de advocacia) em cerca de metade das vendas de Sprint e Scale.
A18: Especialistas na entrega (% da receita de Sprint e Scale) | B18: 0.35 | C18: Gestores e empresários experientes pagos por projeto: é o know-how que o pitch apresenta como diferencial. Lançado no mês da venda, junto com a receita.
A19: Deslocamento por Sprint (R$) | B19: 600 | C19: Transporte e alimentação nos 7 dias de imersão na Grande SP.
A20: Deslocamento por Scale vendido (R$) | B20: 1200 | C20: 6 visitas mensais de acompanhamento (R$ 200 cada), lançadas no mês da venda.
A22: 3. SIMPLES NACIONAL – ANEXO V (LC 123/2006)
A23: Faixa (receita bruta dos últimos 12 meses) | B23: RBT12 a partir de (R$) | C23: Alíquota nominal | D23: Parcela a deduzir (R$)
A24: 1ª faixa – até R$ 180 mil | B24: 0 | C24: 0.155 | D24: 0
A25: 2ª faixa – até R$ 360 mil | B25: 180000.01 | C25: 0.18 | D25: 4500
A26: 3ª faixa – até R$ 720 mil | B26: 360000.01 | C26: 0.195 | D26: 9900
A27: 4ª faixa – até R$ 1,8 mi | B27: 720000.01 | C27: 0.205 | D27: 17100
A28: 5ª faixa – até R$ 3,6 mi | B28: 1800000 | C28: 0.23 | D28: 62100
A29: 6ª faixa – até R$ 4,8 mi | B29: 3600000 | C29: 0.305 | D29: 540000
A30: SaaS e consultoria de gestão ficam no Anexo V enquanto o Fator R (folha ÷ receita) for menor que 28%. Alíquota efetiva = (RBT12 × alíquota nominal − parcela a deduzir) ÷ RBT12. No 1º ano, RBT12 = média dos meses anteriores × 12.
A32: 4. DESPESAS FIXAS (R$/mês, sem a retirada dos sócios)
A33: Aluguel e condomínio – escritório virtual | B33: 150 | C33: Endereço fiscal com sala de reunião sob demanda: planos a partir de R$ 80/mês na Av. Paulista (Company Hero) + uso avulso de sala.
A34: Salários + encargos (CLT) | B34: 0 | C34: Sem funcionários CLT fixos: o suporte aos clientes cresce com a base e está nas despesas variáveis (seção 10).
A35: Contador | B35: 400 | C35: Contabilidade online para serviços: R$ 120–400/mês (contabilidade.com, 2026). Topo da faixa por ter 7 sócios com retirada.
A36: Energia, água, gás | B36: 0 | C36: Equipe remota, sem sede física.
A37: Internet e telefone | B37: 200 | C37: 2 linhas corporativas + WhatsApp Business.
A38: Marketing / redes sociais | B38: 3500 | C38: Marca e conteúdo (LinkedIn, Instagram, eventos de associações). A mídia paga por cliente novo está na seção 10.
A39: Softwares e assinaturas | B39: 1500 | C39: Google Workspace (7 contas), CRM, ferramentas de IA para desenvolvimento, design e assinatura eletrônica.
A40: Desenvolvedor auxiliar PJ (meio período, 20 h/semana) | B40: 5000 | C40: Metade da faixa de dev pleno PJ (R$ 10–18 mil/mês, Jobrise 2026; Robert Half: mediana R$ 12 mil). Os sócios seguem construindo junto.
A41: Nuvem, banco de dados e segurança (base fixa) | B41: 1250 | C41: Hospedagem, banco de dados, backups e monitoramento. O consumo por cliente está na linha de tokens.
A42: TOTAL DAS DESPESAS FIXAS SEM RETIRADA | B42: =SUM(B33:B41) -> 12000 | C42: É o custo mensal da Precept com receita zero: base do cálculo de runway.
A44: 5. RETIRADA DOS SÓCIOS (pró-labore)
A45: Número de sócios | B45: 7 | C45: Quadro societário da Precept: todos recebem a mesma quantia.
A46: Retirada por sócio (% da receita bruta do mês) | B46: 0.035 | C46: Igual para os 7 sócios, a partir do mês 4. Com a escada de vendas do Core, o break-even acontece no mês 3, antes de a retirada começar.
A47: Mês em que a retirada começa | B47: 4 | C47: Decisão do grupo (3º ou 4º mês). O mês 4 deixa o 1º trimestre só para validar o MVP e reduz a necessidade de caixa.
A48: Retirada total (% da receita bruta) | B48: =B45*B46 -> 0.245 | C48: Nº de sócios × % por sócio.
A50: 6. INVESTIMENTO INICIAL (PERÍODO 0) E CAPITAL
A51: Máquinas e equipamentos | B51: 12000 | C51: 2 notebooks de desenvolvimento (~R$ 5.500 cada) + monitor e periféricos (~R$ 1.000).
A52: Móveis e utensílios | B52: 0 | C52: Não se aplica: equipe remota, sem sede.
A53: Reforma / instalação | B53: 0 | C53: Não se aplica: sem sede física.
A54: Abertura da empresa e licenças | B54: 2500 | C54: JUCESP R$ 132,55; e-CNPJ ~R$ 200; taxas municipais ~R$ 500; marca no INPI R$ 440 por classe (classes 35 e 42, com desconto de ME); honorários de abertura.
A55: Estoque inicial | B55: 0 | C55: Não se aplica: serviço digital, sem estoque.
A56: Desenvolvimento do MVP (sócios + devs auxiliares, 3 meses) | B56: 57000 | C56: 1 dev pleno PJ (R$ 10 mil/mês) + 1 dev júnior PJ (R$ 6 mil/mês) por 3 meses = R$ 48 mil; design UX/UI R$ 6 mil; tokens de IA e nuvem do período R$ 3 mil.
A57: Jurídico/LGPD, segurança, identidade visual, site e pré-lançamento | B57: 30500 | C57: Contrato social, acordo de sócios, termos de uso, política de privacidade, DPA e contratos com cessão de PI R$ 10 mil; teste de segurança R$ 5 mil; identidade visual e site R$ 5,5 mil; pré-lançamento R$ 10 mil.
A58: TOTAL DO INVESTIMENTO INICIAL (D) | B58: =SUM(B51:B57) -> 102000 | C58: Vai para o período 0 da aba Fluxo de Caixa.
A59: Capital inicial dos sócios | B59: 150000 | C59: Capital apresentado no pitch (slide 14): custeia tokens, IAs, programa e sistema.
A61: 7. TAXA DE DESCONTO (TMA)
A62: CDI de referência (% a.a.) | B62: 0.1365 | C62: Selic em 13,75% a.a. (Copom, 16/09/2026). CDI ≈ Selic − 0,10 p.p.
A63: Prêmio pelo risco do negócio (p.p. a.a.) | B63: 0.1035 | C63: Risco entre Moderado e Alto na tabela da disciplina. É um produto novo, mas num mercado validado por benchmarks: ADVBOX (+5 mil escritórios, planos até R$ 1.800/mês), G4 Educação (R$ 509 mi/ano com gestão para PMEs), AB2L (+600 lawtechs). Como ainda não há vendas, fica no topo da faixa Moderada.
A64: TMA do grupo (% a.a.) | B64: =B62+B63 -> 0.24 | C64: Vai para a aba VPL e TIR. Também é a taxa da seção 6 da ficha.
A66: 8. INDICADORES-CHAVE (automático)
A67: Runway sem receita (meses) | B67: =(B59-B58)/B42 -> 4 | C67: (Capital − investimento) ÷ despesas fixas sem retirada. Meta do pitch: 4 meses.
A68: Break-even operacional (1º mês com resultado ≥ 0) | B68: =IFERROR(INDEX('Projeção Mensal'!A6:A29,MATCH("Sim",'Projeção Mensal'!AC6:AC29,0)),"Não atinge") -> 3 | C68: Primeiro mês em que a receita cobre todas as despesas.
A69: Necessidade máxima de caixa | B69: ='Necessidade de Caixa e Payback'!F32 -> 118526.3 | C69: Investimento + prejuízos acumulados até o pior momento.
A70: Folga do capital inicial | B70: =B59-B69 -> 31473.7 | C70: Capital − necessidade máxima. Positivo = os R$ 150 mil bastam, com sobra de reserva.
A71: VPL | B71: ='VPL e TIR'!B38 -> 1220849.3 | C71: Copiado da aba VPL e TIR.
A72: TIR equivalente ao ano | B72: ='VPL e TIR'!B40 -> 7.5882793 | C72: Compare com a TMA da linha 64.
A73: Payback simples (período) | B73: ='VPL e TIR'!B43 -> 9 | C73: 1º mês com saldo acumulado ≥ 0.
A74: Payback descontado (período) | B74: ='VPL e TIR'!B44 -> 10 | C74: 1º mês com VP acumulado ≥ 0.
A75: Retirada média por sócio na Estabilidade (R$/mês) | B75: =AVERAGE('Projeção Mensal'!AB18:AB29) -> 16182.918 | C75: Meses 13 a 24.
A77: 9. SENSIBILIDADE DO VPL À TMA
A78: TMA (% a.a.) | B78: VPL (R$) | C78: Leitura
A79: 0.2 | B79: ='Fluxo de Caixa'!$G$5+NPV((1+A79)^(1/12)-1,'Fluxo de Caixa'!$G$6:$G$29) -> 1286100 | C79: =IF(B79>0,"Viável a esta taxa","Inviável a esta taxa") -> Viável a esta taxa
A80: 0.24 | B80: ='Fluxo de Caixa'!$G$5+NPV((1+A80)^(1/12)-1,'Fluxo de Caixa'!$G$6:$G$29) -> 1220849.3 | C80: =IF(B80>0,"Viável a esta taxa","Inviável a esta taxa") -> Viável a esta taxa
A81: 0.27 | B81: ='Fluxo de Caixa'!$G$5+NPV((1+A81)^(1/12)-1,'Fluxo de Caixa'!$G$6:$G$29) -> 1175351 | C81: =IF(B81>0,"Viável a esta taxa","Inviável a esta taxa") -> Viável a esta taxa
A82: 0.29 | B82: ='Fluxo de Caixa'!$G$5+NPV((1+A82)^(1/12)-1,'Fluxo de Caixa'!$G$6:$G$29) -> 1146519.9 | C82: =IF(B82>0,"Viável a esta taxa","Inviável a esta taxa") -> Viável a esta taxa
A83: 0.33 | B83: ='Fluxo de Caixa'!$G$5+NPV((1+A83)^(1/12)-1,'Fluxo de Caixa'!$G$6:$G$29) -> 1092168.3 | C83: =IF(B83>0,"Viável a esta taxa","Inviável a esta taxa") -> Viável a esta taxa
A84: 20–24% = risco Moderado · 24–29% = risco Alto · acima de 29% = risco Muito alto (tabela da disciplina).
A86: 10. VENDAS DO CORE EM ESCADA E CUSTOS POR CLIENTE
A87: Vendas do Core nos meses 1 a 4 (clientes novos) | B87: 3, 5, 7, 10 | C87: Decisão do grupo. Os quatro valores ficam na coluna B da aba Projeção Mensal (células cinzas dos meses 1 a 4).
A88: Crescimento mensal das vendas do Core a partir do mês 5 | B88: 0.05 | C88: Escada exponencial: as vendas do mês 4 (10) crescem 5% ao mês (≈ 80% ao ano), chegando a 27 clientes novos no mês 24. Teste 0%, 3% ou 8% para ver a sensibilidade.
A89: Churn mensal do Core (% da base que cancela) | B89: 0.03 | C89: Benchmark de SaaS B2B para pequenas empresas: 30% a 50% ao ano (≈ 3% a 5% ao mês); meta abaixo de 2% ao mês (UserJot e Vitally, 2025).
A90: Suporte e sucesso do cliente (R$ por cliente ativo/mês) | B90: 150 | C90: 1 analista de suporte (≈ R$ 4.500 + encargos ≈ R$ 7.500/mês) para cada 50 escritórios. Cresce com a base de clientes.
A91: Custo de aquisição por cliente novo do Core (R$) | B91: 1000 | C91: Mídia paga e comissão de parceiros por escritório conquistado. Mantém o CAC de ~R$ 1.000 usado no cálculo de LTV/CAC.
A92: Meses de Core grátis por Sprint vendido | B92: 1 | C92: Decisão do grupo: quem compra o Sprint ganha 1 mês de Core.
A93: Meses de Core grátis por Scale vendido | B93: 3 | C93: Decisão do grupo: quem compra o Scale ganha 3 meses de Core.
A95: 11. LUCRO PRESUMIDO (quando a receita dos últimos 12 meses passa de R$ 4,8 mi)
A96: Limite do Simples Nacional (RBT12, R$) | B96: 4800000 | C96: LC 123/2006, art. 3º: acima disso a empresa sai do Simples. Simplificação: o modelo troca de regime no mês em que o RBT12 passa do limite.
A97: Presunção de lucro para serviços | B97: 0.32 | C97: Lei 9.249/1995, art. 15: 32% da receita para prestação de serviços.
A98: IRPJ sobre o lucro presumido | B98: 0.15 | C98: 15% + adicional de 10% sobre a parcela do lucro presumido acima de R$ 20 mil por mês.
A99: CSLL sobre o lucro presumido | B99: 0.09 | C99: 9% sobre a mesma base de 32%.
A100: PIS + COFINS (regime cumulativo) | B100: 0.0365 | C100: 0,65% + 3,00% sobre a receita.
A101: ISS (São Paulo) | B101: 0.05 | C101: Alíquota máxima de 5%, usada por prudência (a licença de software tem alíquota menor em SP). Vale também no Simples acima do sublimite (linha 102).
A102: Sublimite do ISS no Simples (RBT12, R$) | B102: 3600000 | C102: LC 123/2006, art. 13-A: acima de R$ 3,6 mi o ISS deixa de ser recolhido no DAS e é pago à parte ao município (por isso a 6ª faixa do Anexo V tem alíquota efetiva menor).

Sheet Projeção Mensal
A1: PROJEÇÃO MENSAL DA PRECEPT – 24 MESES
A2: Cinza = vendas (Core nos meses 1 a 4, Sprint e Scale). Do mês 5 em diante, as vendas do Core crescem pela taxa da Premissa 88. Azul = automático. As colunas K, W e Z alimentam a aba Fluxo de Caixa.
A4: Mês | B4: Clientes novos do Core | C4: Clientes Core ativos | D4: Sprints vendidos | E4: Scales vendidos | F4: Meses de Core grátis | G4: Clientes Core pagantes | H4: Receita Core (R$) | I4: Receita Sprint (R$) | J4: Receita Scale (R$) | K4: Vendas Brutas (R$) | L4: Receita últimos 12 meses (R$) | M4: Regime tributário | N4: Alíquota efetiva | O4: Impostos (R$) | P4: Tokens IA (R$) | Q4: Suporte ao cliente (R$) | R4: Meio de pagamento (R$) | S4: Aquisição de clientes Core (R$) | T4: Comissões Sprint/Scale (R$) | U4: Especialistas (R$) | V4: Deslocamento (R$) | W4: Despesas Variáveis (R$) | X4: Fixo base (R$) | Y4: Retirada dos sócios (R$) | Z4: Despesas Fixas (R$) | AA4: Resultado Operacional (R$) | AB4: Retirada por sócio (R$) | AC4: Resultado ≥ 0?
A5: 0 | B5: 0 | C5: 0 | D5: 0 | E5: 0 | F5: 0 | G5: 0 | H5: 0 | I5: 0 | J5: 0 | K5: 0 | L5: 0 | M5: – | O5: 0 | P5: 0 | Q5: 0 | R5: 0 | S5: 0 | T5: 0 | U5: 0 | V5: 0 | W5: 0 | X5: 0 | Y5: 0 | Z5: 0 | AA5: 0 | AB5: 0 | AC5: –
A6: 1 | B6: 3 | C6: =C5-ROUND(C5*'Premissas Precept'!$B$89,0)+B6 -> 3 | D6: 0 | E6: 0 | F6: =D6*'Premissas Precept'!$B$92+SUMPRODUCT(($A$6:$A$29>A6-'Premissas Precept'!$B$93)*($A$6:$A$29<=A6)*$E$6:$E$29) -> 0 | G6: =MAX(0,C6-F6) -> 3 | H6: =G6*'Premissas Precept'!$B$8 -> 5988 | I6: =D6*'Premissas Precept'!$B$9 -> 0 | J6: =E6*'Premissas Precept'!$B$10 -> 0 | K6: =H6+I6+J6 -> 5988 | L6: =K6*12 -> 71856 | M6: =IF(L6<='Premissas Precept'!$B$96,"Simples","Presumido") -> Simples | N6: =IF(M6="Simples",IF(L6<=0,'Premissas Precept'!$C$24,(L6*LOOKUP(L6,'Premissas Precept'!$B$24:$B$29,'Premissas Precept'!$C$24:$C$29)-LOOKUP(L6,'Premissas Precept'!$B$24:$B$29,'Premissas Precept'!$D$24:$D$29))/L6)+IF(L6>'Premissas Precept'!$B$102,'Premissas Precept'!$B$101,0),(('Premissas Precept'!$B$98+'Premissas Precept'!$B$99)*'Premissas Precept'!$B$97*K6+0.1*MAX(0,'Premissas Precept'!$B$97*K6-20000)+('Premissas Precept'!$B$100+'Premissas Precept'!$B$101)*K6)/K6) -> 0.155 | O6: =K6*N6 -> 928.14 | P6: =C6*'Premissas Precept'!$B$15 -> 270 | Q6: =C6*'Premissas Precept'!$B$90 -> 450 | R6: =K6*'Premissas Precept'!$B$16 -> 119.76 | S6: =B6*'Premissas Precept'!$B$91 -> 3000 | T6: =(I6+J6)*'Premissas Precept'!$B$17 -> 0 | U6: =(I6+J6)*'Premissas Precept'!$B$18 -> 0 | V6: =D6*'Premissas Precept'!$B$19+E6*'Premissas Precept'!$B$20 -> 0 | W6: =SUM(O6:V6) -> 4767.9 | X6: ='Premissas Precept'!$B$42 -> 12000 | Y6: =IF(A6>='Premissas Precept'!$B$47,'Premissas Precept'!$B$48*K6,0) -> 0 | Z6: =X6+Y6 -> 12000 | AA6: =K6-W6-Z6 -> -10779.9 | AB6: =Y6/'Premissas Precept'!$B$45 -> 0 | AC6: =IF(AA6>=0,"Sim","Não") -> Não
A7: 2 | B7: 5 | C7: =C6-ROUND(C6*'Premissas Precept'!$B$89,0)+B7 -> 8 | D7: 0 | E7: 0 | F7: =D7*'Premissas Precept'!$B$92+SUMPRODUCT(($A$6:$A$29>A7-'Premissas Precept'!$B$93)*($A$6:$A$29<=A7)*$E$6:$E$29) -> 0 | G7: =MAX(0,C7-F7) -> 8 | H7: =G7*'Premissas Precept'!$B$8 -> 15968 | I7: =D7*'Premissas Precept'!$B$9 -> 0 | J7: =E7*'Premissas Precept'!$B$10 -> 0 | K7: =H7+I7+J7 -> 15968 | L7: =AVERAGE(K$6:K6)*12 -> 71856 | M7: =IF(L7<='Premissas Precept'!$B$96,"Simples","Presumido") -> Simples | N7: =IF(M7="Simples",IF(L7<=0,'Premissas Precept'!$C$24,(L7*LOOKUP(L7,'Premissas Precept'!$B$24:$B$29,'Premissas Precept'!$C$24:$C$29)-LOOKUP(L7,'Premissas Precept'!$B$24:$B$29,'Premissas Precept'!$D$24:$D$29))/L7)+IF(L7>'Premissas Precept'!$B$102,'Premissas Precept'!$B$101,0),(('Premissas Precept'!$B$98+'Premissas Precept'!$B$99)*'Premissas Precept'!$B$97*K7+0.1*MAX(0,'Premissas Precept'!$B$97*K7-20000)+('Premissas Precept'!$B$100+'Premissas Precept'!$B$101)*K7)/K7) -> 0.155 | O7: =K7*N7 -> 2475.04 | P7: =C7*'Premissas Precept'!$B$15 -> 720 | Q7: =C7*'Premissas Precept'!$B$90 -> 1200 | R7: =K7*'Premissas Precept'!$B$16 -> 319.36 | S7: =B7*'Premissas Precept'!$B$91 -> 5000 | T7: =(I7+J7)*'Premissas Precept'!$B$17 -> 0 | U7: =(I7+J7)*'Premissas Precept'!$B$18 -> 0 | V7: =D7*'Premissas Precept'!$B$19+E7*'Premissas Precept'!$B$20 -> 0 | W7: =SUM(O7:V7) -> 9714.4 | X7: ='Premissas Precept'!$B$42 -> 12000 | Y7: =IF(A7>='Premissas Precept'!$B$47,'Premissas Precept'!$B$48*K7,0) -> 0 | Z7: =X7+Y7 -> 12000 | AA7: =K7-W7-Z7 -> -5746.4 | AB7: =Y7/'Premissas Precept'!$B$45 -> 0 | AC7: =IF(AA7>=0,"Sim","Não") -> Não
A8: 3 | B8: 7 | C8: =C7-ROUND(C7*'Premissas Precept'!$B$89,0)+B8 -> 15 | D8: 0 | E8: 0 | F8: =D8*'Premissas Precept'!$B$92+SUMPRODUCT(($A$6:$A$29>A8-'Premissas Precept'!$B$93)*($A$6:$A$29<=A8)*$E$6:$E$29) -> 0 | G8: =MAX(0,C8-F8) -> 15 | H8: =G8*'Premissas Precept'!$B$8 -> 29940 | I8: =D8*'Premissas Precept'!$B$9 -> 0 | J8: =E8*'Premissas Precept'!$B$10 -> 0 | K8: =H8+I8+J8 -> 29940 | L8: =AVERAGE(K$6:K7)*12 -> 131736 | M8: =IF(L8<='Premissas Precept'!$B$96,"Simples","Presumido") -> Simples | N8: =IF(M8="Simples",IF(L8<=0,'Premissas Precept'!$C$24,(L8*LOOKUP(L8,'Premissas Precept'!$B$24:$B$29,'Premissas Precept'!$C$24:$C$29)-LOOKUP(L8,'Premissas Precept'!$B$24:$B$29,'Premissas Precept'!$D$24:$D$29))/L8)+IF(L8>'Premissas Precept'!$B$102,'Premissas Precept'!$B$101,0),(('Premissas Precept'!$B$98+'Premissas Precept'!$B$99)*'Premissas Precept'!$B$97*K8+0.1*MAX(0,'Premissas Precept'!$B$97*K8-20000)+('Premissas Precept'!$B$100+'Premissas Precept'!$B$101)*K8)/K8) -> 0.155 | O8: =K8*N8 -> 4640.7 | P8: =C8*'Premissas Precept'!$B$15 -> 1350 | Q8: =C8*'Premissas Precept'!$B$90 -> 2250 | R8: =K8*'Premissas Precept'!$B$16 -> 598.8 | S8: =B8*'Premissas Precept'!$B$91 -> 7000 | T8: =(I8+J8)*'Premissas Precept'!$B$17 -> 0 | U8: =(I8+J8)*'Premissas Precept'!$B$18 -> 0 | V8: =D8*'Premissas Precept'!$B$19+E8*'Premissas Precept'!$B$20 -> 0 | W8: =SUM(O8:V8) -> 15839.5 | X8: ='Premissas Precept'!$B$42 -> 12000 | Y8: =IF(A8>='Premissas Precept'!$B$47,'Premissas Precept'!$B$48*K8,0) -> 0 | Z8: =X8+Y8 -> 12000 | AA8: =K8-W8-Z8 -> 2100.5 | AB8: =Y8/'Premissas Precept'!$B$45 -> 0 | AC8: =IF(AA8>=0,"Sim","Não") -> Sim
A9: 4 | B9: 10 | C9: =C8-ROUND(C8*'Premissas Precept'!$B$89,0)+B9 -> 25 | D9: 1 | E9: 0 | F9: =D9*'Premissas Precept'!$B$92+SUMPRODUCT(($A$6:$A$29>A9-'Premissas Precept'!$B$93)*($A$6:$A$29<=A9)*$E$6:$E$29) -> 1 | G9: =MAX(0,C9-F9) -> 24 | H9: =G9*'Premissas Precept'!$B$8 -> 47904 | I9: =D9*'Premissas Precept'!$B$9 -> 9997 | J9: =E9*'Premissas Precept'!$B$10 -> 0 | K9: =H9+I9+J9 -> 57901 | L9: =AVERAGE(K$6:K8)*12 -> 207584 | M9: =IF(L9<='Premissas Precept'!$B$96,"Simples","Presumido") -> Simples | N9: =IF(M9="Simples",IF(L9<=0,'Premissas Precept'!$C$24,(L9*LOOKUP(L9,'Premissas Precept'!$B$24:$B$29,'Premissas Precept'!$C$24:$C$29)-LOOKUP(L9,'Premissas Precept'!$B$24:$B$29,'Premissas Precept'!$D$24:$D$29))/L9)+IF(L9>'Premissas Precept'!$B$102,'Premissas Precept'!$B$101,0),(('Premissas Precept'!$B$98+'Premissas Precept'!$B$99)*'Premissas Precept'!$B$97*K9+0.1*MAX(0,'Premissas Precept'!$B$97*K9-20000)+('Premissas Precept'!$B$100+'Premissas Precept'!$B$101)*K9)/K9) -> 0.15832203 | O9: =K9*N9 -> 9167.0038 | P9: =C9*'Premissas Precept'!$B$15 -> 2250 | Q9: =C9*'Premissas Precept'!$B$90 -> 3750 | R9: =K9*'Premissas Precept'!$B$16 -> 1158.02 | S9: =B9*'Premissas Precept'!$B$91 -> 10000 | T9: =(I9+J9)*'Premissas Precept'!$B$17 -> 499.85 | U9: =(I9+J9)*'Premissas Precept'!$B$18 -> 3498.95 | V9: =D9*'Premissas Precept'!$B$19+E9*'Premissas Precept'!$B$20 -> 600 | W9: =SUM(O9:V9) -> 30923.824 | X9: ='Premissas Precept'!$B$42 -> 12000 | Y9: =IF(A9>='Premissas Precept'!$B$47,'Premissas Precept'!$B$48*K9,0) -> 14185.745 | Z9: =X9+Y9 -> 26185.745 | AA9: =K9-W9-Z9 -> 791.43122 | AB9: =Y9/'Premissas Precept'!$B$45 -> 2026.535 | AC9: =IF(AA9>=0,"Sim","Não") -> Sim
A10: 5 | B10: =ROUND($B$9*(1+'Premissas Precept'!$B$88)^(A10-4),0) -> 11 | C10: =C9-ROUND(C9*'Premissas Precept'!$B$89,0)+B10 -> 35 | D10: 1 | E10: 0 | F10: =D10*'Premissas Precept'!$B$92+SUMPRODUCT(($A$6:$A$29>A10-'Premissas Precept'!$B$93)*($A$6:$A$29<=A10)*$E$6:$E$29) -> 1 | G10: =MAX(0,C10-F10) -> 34 | H10: =G10*'Premissas Precept'!$B$8 -> 67864 | I10: =D10*'Premissas Precept'!$B$9 -> 9997 | J10: =E10*'Premissas Precept'!$B$10 -> 0 | K10: =H10+I10+J10 -> 77861 | L10: =AVERAGE(K$6:K9)*12 -> 329391 | M10: =IF(L10<='Premissas Precept'!$B$96,"Simples","Presumido") -> Simples | N10: =IF(M10="Simples",IF(L10<=0,'Premissas Precept'!$C$24,(L10*LOOKUP(L10,'Premissas Precept'!$B$24:$B$29,'Premissas Precept'!$C$24:$C$29)-LOOKUP(L10,'Premissas Precept'!$B$24:$B$29,'Premissas Precept'!$D$24:$D$29))/L10)+IF(L10>'Premissas Precept'!$B$102,'Premissas Precept'!$B$101,0),(('Premissas Precept'!$B$98+'Premissas Precept'!$B$99)*'Premissas Precept'!$B$97*K10+0.1*MAX(0,'Premissas Precept'!$B$97*K10-20000)+('Premissas Precept'!$B$100+'Premissas Precept'!$B$101)*K10)/K10) -> 0.16633842 | O10: =K10*N10 -> 12951.276 | P10: =C10*'Premissas Precept'!$B$15 -> 3150 | Q10: =C10*'Premissas Precept'!$B$90 -> 5250 | R10: =K10*'Premissas Precept'!$B$16 -> 1557.22 | S10: =B10*'Premissas Precept'!$B$91 -> 11000 | T10: =(I10+J10)*'Premissas Precept'!$B$17 -> 499.85 | U10: =(I10+J10)*'Premissas Precept'!$B$18 -> 3498.95 | V10: =D10*'Premissas Precept'!$B$19+E10*'Premissas Precept'!$B$20 -> 600 | W10: =SUM(O10:V10) -> 38507.296 | X10: ='Premissas Precept'!$B$42 -> 12000 | Y10: =IF(A10>='Premissas Precept'!$B$47,'Premissas Precept'!$B$48*K10,0) -> 19075.945 | Z10: =X10+Y10 -> 31075.945 | AA10: =K10-W10-Z10 -> 8277.7589 | AB10: =Y10/'Premissas Precept'!$B$45 -> 2725.135 | AC10: =IF(AA10>=0,"Sim","Não") -> Sim
A11: 6 | B11: =ROUND($B$9*(1+'Premissas Precept'!$B$88)^(A11-4),0) -> 11 | C11: =C10-ROUND(C10*'Premissas Precept'!$B$89,0)+B11 -> 45 | D11: 1 | E11: 1 | F11: =D11*'Premissas Precept'!$B$92+SUMPRODUCT(($A$6:$A$29>A11-'Premissas Precept'!$B$93)*($A$6:$A$29<=A11)*$E$6:$E$29) -> 2 | G11: =MAX(0,C11-F11) -> 43 | H11: =G11*'Premissas Precept'!$B$8 -> 85828 | I11: =D11*'Premissas Precept'!$B$9 -> 9997 | J11: =E11*'Premissas Precept'!$B$10 -> 29997 | K11: =H11+I11+J11 -> 125822 | L11: =AVERAGE(K$6:K10)*12 -> 450379.2 | M11: =IF(L11<='Premissas Precept'!$B$96,"Simples","Presumido") -> Simples | N11: =IF(M11="Simples",IF(L11<=0,'Premissas Precept'!$C$24,(L11*LOOKUP(L11,'Premissas Precept'!$B$24:$B$29,'Premissas Precept'!$C$24:$C$29)-LOOKUP(L11,'Premissas Precept'!$B$24:$B$29,'Premissas Precept'!$D$24:$D$29))/L11)+IF(L11>'Premissas Precept'!$B$102,'Premissas Precept'!$B$101,0),(('Premissas Precept'!$B$98+'Premissas Precept'!$B$99)*'Premissas Precept'!$B$97*K11+0.1*MAX(0,'Premissas Precept'!$B$97*K11-20000)+('Premissas Precept'!$B$100+'Premissas Precept'!$B$101)*K11)/K11) -> 0.17301852 | O11: =K11*N11 -> 21769.537 | P11: =C11*'Premissas Precept'!$B$15 -> 4050 | Q11: =C11*'Premissas Precept'!$B$90 -> 6750 | R11: =K11*'Premissas Precept'!$B$16 -> 2516.44 | S11: =B11*'Premissas Precept'!$B$91 -> 11000 | T11: =(I11+J11)*'Premissas Precept'!$B$17 -> 1999.7 | U11: =(I11+J11)*'Premissas Precept'!$B$18 -> 13997.9 | V11: =D11*'Premissas Precept'!$B$19+E11*'Premissas Precept'!$B$20 -> 1800 | W11: =SUM(O11:V11) -> 63883.577 | X11: ='Premissas Precept'!$B$42 -> 12000 | Y11: =IF(A11>='Premissas Precept'!$B$47,'Premissas Precept'!$B$48*K11,0) -> 30826.39 | Z11: =X11+Y11 -> 42826.39 | AA11: =K11-W11-Z11 -> 19112.033 | AB11: =Y11/'Premissas Precept'!$B$45 -> 4403.77 | AC11: =IF(AA11>=0,"Sim","Não") -> Sim
A12: 7 | B12: =ROUND($B$9*(1+'Premissas Precept'!$B$88)^(A12-4),0) -> 12 | C12: =C11-ROUND(C11*'Premissas Precept'!$B$89,0)+B12 -> 56 | D12: 1 | E12: 0 | F12: =D12*'Premissas Precept'!$B$92+SUMPRODUCT(($A$6:$A$29>A12-'Premissas Precept'!$B$93)*($A$6:$A$29<=A12)*$E$6:$E$29) -> 2 | G12: =MAX(0,C12-F12) -> 54 | H12: =G12*'Premissas Precept'!$B$8 -> 107784 | I12: =D12*'Premissas Precept'!$B$9 -> 9997 | J12: =E12*'Premissas Precept'!$B$10 -> 0 | K12: =H12+I12+J12 -> 117781 | L12: =AVERAGE(K$6:K11)*12 -> 626960 | M12: =IF(L12<='Premissas Precept'!$B$96,"Simples","Presumido") -> Simples | N12: =IF(M12="Simples",IF(L12<=0,'Premissas Precept'!$C$24,(L12*LOOKUP(L12,'Premissas Precept'!$B$24:$B$29,'Premissas Precept'!$C$24:$C$29)-LOOKUP(L12,'Premissas Precept'!$B$24:$B$29,'Premissas Precept'!$D$24:$D$29))/L12)+IF(L12>'Premissas Precept'!$B$102,'Premissas Precept'!$B$101,0),(('Premissas Precept'!$B$98+'Premissas Precept'!$B$99)*'Premissas Precept'!$B$97*K12+0.1*MAX(0,'Premissas Precept'!$B$97*K12-20000)+('Premissas Precept'!$B$100+'Premissas Precept'!$B$101)*K12)/K12) -> 0.17920952 | O12: =K12*N12 -> 21107.476 | P12: =C12*'Premissas Precept'!$B$15 -> 5040 | Q12: =C12*'Premissas Precept'!$B$90 -> 8400 | R12: =K12*'Premissas Precept'!$B$16 -> 2355.62 | S12: =B12*'Premissas Precept'!$B$91 -> 12000 | T12: =(I12+J12)*'Premissas Precept'!$B$17 -> 499.85 | U12: =(I12+J12)*'Premissas Precept'!$B$18 -> 3498.95 | V12: =D12*'Premissas Precept'!$B$19+E12*'Premissas Precept'!$B$20 -> 600 | W12: =SUM(O12:V12) -> 53501.896 | X12: ='Premissas Precept'!$B$42 -> 12000 | Y12: =IF(A12>='Premissas Precept'!$B$47,'Premissas Precept'!$B$48*K12,0) -> 28856.345 | Z12: =X12+Y12 -> 40856.345 | AA12: =K12-W12-Z12 -> 23422.759 | AB12: =Y12/'Premissas Precept'!$B$45 -> 4122.335 | AC12: =IF(AA12>=0,"Sim","Não") -> Sim
A13: 8 | B13: =ROUND($B$9*(1+'Premissas Precept'!$B$88)^(A13-4),0) -> 12 | C13: =C12-ROUND(C12*'Premissas Precept'!$B$89,0)+B13 -> 66 | D13: 1 | E13: 1 | F13: =D13*'Premissas Precept'!$B$92+SUMPRODUCT(($A$6:$A$29>A13-'Premissas Precept'!$B$93)*($A$6:$A$29<=A13)*$E$6:$E$29) -> 3 | G13: =MAX(0,C13-F13) -> 63 | H13: =G13*'Premissas Precept'!$B$8 -> 125748 | I13: =D13*'Premissas Precept'!$B$9 -> 9997 | J13: =E13*'Premissas Precept'!$B$10 -> 29997 | K13: =H13+I13+J13 -> 165742 | L13: =AVERAGE(K$6:K12)*12 -> 739304.57 | M13: =IF(L13<='Premissas Precept'!$B$96,"Simples","Presumido") -> Simples | N13: =IF(M13="Simples",IF(L13<=0,'Premissas Precept'!$C$24,(L13*LOOKUP(L13,'Premissas Precept'!$B$24:$B$29,'Premissas Precept'!$C$24:$C$29)-LOOKUP(L13,'Premissas Precept'!$B$24:$B$29,'Premissas Precept'!$D$24:$D$29))/L13)+IF(L13>'Premissas Precept'!$B$102,'Premissas Precept'!$B$101,0),(('Premissas Precept'!$B$98+'Premissas Precept'!$B$99)*'Premissas Precept'!$B$97*K13+0.1*MAX(0,'Premissas Precept'!$B$97*K13-20000)+('Premissas Precept'!$B$100+'Premissas Precept'!$B$101)*K13)/K13) -> 0.18187016 | O13: =K13*N13 -> 30143.523 | P13: =C13*'Premissas Precept'!$B$15 -> 5940 | Q13: =C13*'Premissas Precept'!$B$90 -> 9900 | R13: =K13*'Premissas Precept'!$B$16 -> 3314.84 | S13: =B13*'Premissas Precept'!$B$91 -> 12000 | T13: =(I13+J13)*'Premissas Precept'!$B$17 -> 1999.7 | U13: =(I13+J13)*'Premissas Precept'!$B$18 -> 13997.9 | V13: =D13*'Premissas Precept'!$B$19+E13*'Premissas Precept'!$B$20 -> 1800 | W13: =SUM(O13:V13) -> 79095.963 | X13: ='Premissas Precept'!$B$42 -> 12000 | Y13: =IF(A13>='Premissas Precept'!$B$47,'Premissas Precept'!$B$48*K13,0) -> 40606.79 | Z13: =X13+Y13 -> 52606.79 | AA13: =K13-W13-Z13 -> 34039.247 | AB13: =Y13/'Premissas Precept'!$B$45 -> 5800.97 | AC13: =IF(AA13>=0,"Sim","Não") -> Sim
A14: 9 | B14: =ROUND($B$9*(1+'Premissas Precept'!$B$88)^(A14-4),0) -> 13 | C14: =C13-ROUND(C13*'Premissas Precept'!$B$89,0)+B14 -> 77 | D14: 2 | E14: 0 | F14: =D14*'Premissas Precept'!$B$92+SUMPRODUCT(($A$6:$A$29>A14-'Premissas Precept'!$B$93)*($A$6:$A$29<=A14)*$E$6:$E$29) -> 3 | G14: =MAX(0,C14-F14) -> 74 | H14: =G14*'Premissas Precept'!$B$8 -> 147704 | I14: =D14*'Premissas Precept'!$B$9 -> 19994 | J14: =E14*'Premissas Precept'!$B$10 -> 0 | K14: =H14+I14+J14 -> 167698 | L14: =AVERAGE(K$6:K13)*12 -> 895504.5 | M14: =IF(L14<='Premissas Precept'!$B$96,"Simples","Presumido") -> Simples | N14: =IF(M14="Simples",IF(L14<=0,'Premissas Precept'!$C$24,(L14*LOOKUP(L14,'Premissas Precept'!$B$24:$B$29,'Premissas Precept'!$C$24:$C$29)-LOOKUP(L14,'Premissas Precept'!$B$24:$B$29,'Premissas Precept'!$D$24:$D$29))/L14)+IF(L14>'Premissas Precept'!$B$102,'Premissas Precept'!$B$101,0),(('Premissas Precept'!$B$98+'Premissas Precept'!$B$99)*'Premissas Precept'!$B$97*K14+0.1*MAX(0,'Premissas Precept'!$B$97*K14-20000)+('Premissas Precept'!$B$100+'Premissas Precept'!$B$101)*K14)/K14) -> 0.18590462 | O14: =K14*N14 -> 31175.833 | P14: =C14*'Premissas Precept'!$B$15 -> 6930 | Q14: =C14*'Premissas Precept'!$B$90 -> 11550 | R14: =K14*'Premissas Precept'!$B$16 -> 3353.96 | S14: =B14*'Premissas Precept'!$B$91 -> 13000 | T14: =(I14+J14)*'Premissas Precept'!$B$17 -> 999.7 | U14: =(I14+J14)*'Premissas Precept'!$B$18 -> 6997.9 | V14: =D14*'Premissas Precept'!$B$19+E14*'Premissas Precept'!$B$20 -> 1200 | W14: =SUM(O14:V14) -> 75207.393 | X14: ='Premissas Precept'!$B$42 -> 12000 | Y14: =IF(A14>='Premissas Precept'!$B$47,'Premissas Precept'!$B$48*K14,0) -> 41086.01 | Z14: =X14+Y14 -> 53086.01 | AA14: =K14-W14-Z14 -> 39404.597 | AB14: =Y14/'Premissas Precept'!$B$45 -> 5869.43 | AC14: =IF(AA14>=0,"Sim","Não") -> Sim
A15: 10 | B15: =ROUND($B$9*(1+'Premissas Precept'!$B$88)^(A15-4),0) -> 13 | C15: =C14-ROUND(C14*'Premissas Precept'!$B$89,0)+B15 -> 88 | D15: 1 | E15: 1 | F15: =D15*'Premissas Precept'!$B$92+SUMPRODUCT(($A$6:$A$29>A15-'Premissas Precept'!$B$93)*($A$6:$A$29<=A15)*$E$6:$E$29) -> 3 | G15: =MAX(0,C15-F15) -> 85 | H15: =G15*'Premissas Precept'!$B$8 -> 169660 | I15: =D15*'Premissas Precept'!$B$9 -> 9997 | J15: =E15*'Premissas Precept'!$B$10 -> 29997 | K15: =H15+I15+J15 -> 209654 | L15: =AVERAGE(K$6:K14)*12 -> 1019601.3 | M15: =IF(L15<='Premissas Precept'!$B$96,"Simples","Presumido") -> Simples | N15: =IF(M15="Simples",IF(L15<=0,'Premissas Precept'!$C$24,(L15*LOOKUP(L15,'Premissas Precept'!$B$24:$B$29,'Premissas Precept'!$C$24:$C$29)-LOOKUP(L15,'Premissas Precept'!$B$24:$B$29,'Premissas Precept'!$D$24:$D$29))/L15)+IF(L15>'Premissas Precept'!$B$102,'Premissas Precept'!$B$101,0),(('Premissas Precept'!$B$98+'Premissas Precept'!$B$99)*'Premissas Precept'!$B$97*K15+0.1*MAX(0,'Premissas Precept'!$B$97*K15-20000)+('Premissas Precept'!$B$100+'Premissas Precept'!$B$101)*K15)/K15) -> 0.18822874 | O15: =K15*N15 -> 39462.908 | P15: =C15*'Premissas Precept'!$B$15 -> 7920 | Q15: =C15*'Premissas Precept'!$B$90 -> 13200 | R15: =K15*'Premissas Precept'!$B$16 -> 4193.08 | S15: =B15*'Premissas Precept'!$B$91 -> 13000 | T15: =(I15+J15)*'Premissas Precept'!$B$17 -> 1999.7 | U15: =(I15+J15)*'Premissas Precept'!$B$18 -> 13997.9 | V15: =D15*'Premissas Precept'!$B$19+E15*'Premissas Precept'!$B$20 -> 1800 | W15: =SUM(O15:V15) -> 95573.588 | X15: ='Premissas Precept'!$B$42 -> 12000 | Y15: =IF(A15>='Premissas Precept'!$B$47,'Premissas Precept'!$B$48*K15,0) -> 51365.23 | Z15: =X15+Y15 -> 63365.23 | AA15: =K15-W15-Z15 -> 50715.182 | AB15: =Y15/'Premissas Precept'!$B$45 -> 7337.89 | AC15: =IF(AA15>=0,"Sim","Não") -> Sim
A16: 11 | B16: =ROUND($B$9*(1+'Premissas Precept'!$B$88)^(A16-4),0) -> 14 | C16: =C15-ROUND(C15*'Premissas Precept'!$B$89,0)+B16 -> 99 | D16: 2 | E16: 0 | F16: =D16*'Premissas Precept'!$B$92+SUMPRODUCT(($A$6:$A$29>A16-'Premissas Precept'!$B$93)*($A$6:$A$29<=A16)*$E$6:$E$29) -> 3 | G16: =MAX(0,C16-F16) -> 96 | H16: =G16*'Premissas Precept'!$B$8 -> 191616 | I16: =D16*'Premissas Precept'!$B$9 -> 19994 | J16: =E16*'Premissas Precept'!$B$10 -> 0 | K16: =H16+I16+J16 -> 211610 | L16: =AVERAGE(K$6:K15)*12 -> 1169226 | M16: =IF(L16<='Premissas Precept'!$B$96,"Simples","Presumido") -> Simples | N16: =IF(M16="Simples",IF(L16<=0,'Premissas Precept'!$C$24,(L16*LOOKUP(L16,'Premissas Precept'!$B$24:$B$29,'Premissas Precept'!$C$24:$C$29)-LOOKUP(L16,'Premissas Precept'!$B$24:$B$29,'Premissas Precept'!$D$24:$D$29))/L16)+IF(L16>'Premissas Precept'!$B$102,'Premissas Precept'!$B$101,0),(('Premissas Precept'!$B$98+'Premissas Precept'!$B$99)*'Premissas Precept'!$B$97*K16+0.1*MAX(0,'Premissas Precept'!$B$97*K16-20000)+('Premissas Precept'!$B$100+'Premissas Precept'!$B$101)*K16)/K16) -> 0.19037494 | O16: =K16*N16 -> 40285.241 | P16: =C16*'Premissas Precept'!$B$15 -> 8910 | Q16: =C16*'Premissas Precept'!$B$90 -> 14850 | R16: =K16*'Premissas Precept'!$B$16 -> 4232.2 | S16: =B16*'Premissas Precept'!$B$91 -> 14000 | T16: =(I16+J16)*'Premissas Precept'!$B$17 -> 999.7 | U16: =(I16+J16)*'Premissas Precept'!$B$18 -> 6997.9 | V16: =D16*'Premissas Precept'!$B$19+E16*'Premissas Precept'!$B$20 -> 1200 | W16: =SUM(O16:V16) -> 91475.041 | X16: ='Premissas Precept'!$B$42 -> 12000 | Y16: =IF(A16>='Premissas Precept'!$B$47,'Premissas Precept'!$B$48*K16,0) -> 51844.45 | Z16: =X16+Y16 -> 63844.45 | AA16: =K16-W16-Z16 -> 56290.509 | AB16: =Y16/'Premissas Precept'!$B$45 -> 7406.35 | AC16: =IF(AA16>=0,"Sim","Não") -> Sim
A17: 12 | B17: =ROUND($B$9*(1+'Premissas Precept'!$B$88)^(A17-4),0) -> 15 | C17: =C16-ROUND(C16*'Premissas Precept'!$B$89,0)+B17 -> 111 | D17: 1 | E17: 1 | F17: =D17*'Premissas Precept'!$B$92+SUMPRODUCT(($A$6:$A$29>A17-'Premissas Precept'!$B$93)*($A$6:$A$29<=A17)*$E$6:$E$29) -> 3 | G17: =MAX(0,C17-F17) -> 108 | H17: =G17*'Premissas Precept'!$B$8 -> 215568 | I17: =D17*'Premissas Precept'!$B$9 -> 9997 | J17: =E17*'Premissas Precept'!$B$10 -> 29997 | K17: =H17+I17+J17 -> 255562 | L17: =AVERAGE(K$6:K16)*12 -> 1293780 | M17: =IF(L17<='Premissas Precept'!$B$96,"Simples","Presumido") -> Simples | N17: =IF(M17="Simples",IF(L17<=0,'Premissas Precept'!$C$24,(L17*LOOKUP(L17,'Premissas Precept'!$B$24:$B$29,'Premissas Precept'!$C$24:$C$29)-LOOKUP(L17,'Premissas Precept'!$B$24:$B$29,'Premissas Precept'!$D$24:$D$29))/L17)+IF(L17>'Premissas Precept'!$B$102,'Premissas Precept'!$B$101,0),(('Premissas Precept'!$B$98+'Premissas Precept'!$B$99)*'Premissas Precept'!$B$97*K17+0.1*MAX(0,'Premissas Precept'!$B$97*K17-20000)+('Premissas Precept'!$B$100+'Premissas Precept'!$B$101)*K17)/K17) -> 0.19178292 | O17: =K17*N17 -> 49012.425 | P17: =C17*'Premissas Precept'!$B$15 -> 9990 | Q17: =C17*'Premissas Precept'!$B$90 -> 16650 | R17: =K17*'Premissas Precept'!$B$16 -> 5111.24 | S17: =B17*'Premissas Precept'!$B$91 -> 15000 | T17: =(I17+J17)*'Premissas Precept'!$B$17 -> 1999.7 | U17: =(I17+J17)*'Premissas Precept'!$B$18 -> 13997.9 | V17: =D17*'Premissas Precept'!$B$19+E17*'Premissas Precept'!$B$20 -> 1800 | W17: =SUM(O17:V17) -> 113561.27 | X17: ='Premissas Precept'!$B$42 -> 12000 | Y17: =IF(A17>='Premissas Precept'!$B$47,'Premissas Precept'!$B$48*K17,0) -> 62612.69 | Z17: =X17+Y17 -> 74612.69 | AA17: =K17-W17-Z17 -> 67388.045 | AB17: =Y17/'Premissas Precept'!$B$45 -> 8944.67 | AC17: =IF(AA17>=0,"Sim","Não") -> Sim
A18: 13 | B18: =ROUND($B$9*(1+'Premissas Precept'!$B$88)^(A18-4),0) -> 16 | C18: =C17-ROUND(C17*'Premissas Precept'!$B$89,0)+B18 -> 124 | D18: 4 | E18: 1 | F18: =D18*'Premissas Precept'!$B$92+SUMPRODUCT(($A$6:$A$29>A18-'Premissas Precept'!$B$93)*($A$6:$A$29<=A18)*$E$6:$E$29) -> 6 | G18: =MAX(0,C18-F18) -> 118 | H18: =G18*'Premissas Precept'!$B$8 -> 235528 | I18: =D18*'Premissas Precept'!$B$9 -> 39988 | J18: =E18*'Premissas Precept'!$B$10 -> 29997 | K18: =H18+I18+J18 -> 305513 | L18: =SUM(K6:K17) -> 1441527 | M18: =IF(L18<='Premissas Precept'!$B$96,"Simples","Presumido") -> Simples | N18: =IF(M18="Simples",IF(L18<=0,'Premissas Precept'!$C$24,(L18*LOOKUP(L18,'Premissas Precept'!$B$24:$B$29,'Premissas Precept'!$C$24:$C$29)-LOOKUP(L18,'Premissas Precept'!$B$24:$B$29,'Premissas Precept'!$D$24:$D$29))/L18)+IF(L18>'Premissas Precept'!$B$102,'Premissas Precept'!$B$101,0),(('Premissas Precept'!$B$98+'Premissas Precept'!$B$99)*'Premissas Precept'!$B$97*K18+0.1*MAX(0,'Premissas Precept'!$B$97*K18-20000)+('Premissas Precept'!$B$100+'Premissas Precept'!$B$101)*K18)/K18) -> 0.19313758 | O18: =K18*N18 -> 59006.041 | P18: =C18*'Premissas Precept'!$B$15 -> 11160 | Q18: =C18*'Premissas Precept'!$B$90 -> 18600 | R18: =K18*'Premissas Precept'!$B$16 -> 6110.26 | S18: =B18*'Premissas Precept'!$B$91 -> 16000 | T18: =(I18+J18)*'Premissas Precept'!$B$17 -> 3499.25 | U18: =(I18+J18)*'Premissas Precept'!$B$18 -> 24494.75 | V18: =D18*'Premissas Precept'!$B$19+E18*'Premissas Precept'!$B$20 -> 3600 | W18: =SUM(O18:V18) -> 142470.3 | X18: ='Premissas Precept'!$B$42 -> 12000 | Y18: =IF(A18>='Premissas Precept'!$B$47,'Premissas Precept'!$B$48*K18,0) -> 74850.685 | Z18: =X18+Y18 -> 86850.685 | AA18: =K18-W18-Z18 -> 76192.014 | AB18: =Y18/'Premissas Precept'!$B$45 -> 10692.955 | AC18: =IF(AA18>=0,"Sim","Não") -> Sim
A19: 14 | B19: =ROUND($B$9*(1+'Premissas Precept'!$B$88)^(A19-4),0) -> 16 | C19: =C18-ROUND(C18*'Premissas Precept'!$B$89,0)+B19 -> 136 | D19: 4 | E19: 1 | F19: =D19*'Premissas Precept'!$B$92+SUMPRODUCT(($A$6:$A$29>A19-'Premissas Precept'!$B$93)*($A$6:$A$29<=A19)*$E$6:$E$29) -> 7 | G19: =MAX(0,C19-F19) -> 129 | H19: =G19*'Premissas Precept'!$B$8 -> 257484 | I19: =D19*'Premissas Precept'!$B$9 -> 39988 | J19: =E19*'Premissas Precept'!$B$10 -> 29997 | K19: =H19+I19+J19 -> 327469 | L19: =SUM(K7:K18) -> 1741052 | M19: =IF(L19<='Premissas Precept'!$B$96,"Simples","Presumido") -> Simples | N19: =IF(M19="Simples",IF(L19<=0,'Premissas Precept'!$C$24,(L19*LOOKUP(L19,'Premissas Precept'!$B$24:$B$29,'Premissas Precept'!$C$24:$C$29)-LOOKUP(L19,'Premissas Precept'!$B$24:$B$29,'Premissas Precept'!$D$24:$D$29))/L19)+IF(L19>'Premissas Precept'!$B$102,'Premissas Precept'!$B$101,0),(('Premissas Precept'!$B$98+'Premissas Precept'!$B$99)*'Premissas Precept'!$B$97*K19+0.1*MAX(0,'Premissas Precept'!$B$97*K19-20000)+('Premissas Precept'!$B$100+'Premissas Precept'!$B$101)*K19)/K19) -> 0.19517835 | O19: =K19*N19 -> 63914.86 | P19: =C19*'Premissas Precept'!$B$15 -> 12240 | Q19: =C19*'Premissas Precept'!$B$90 -> 20400 | R19: =K19*'Premissas Precept'!$B$16 -> 6549.38 | S19: =B19*'Premissas Precept'!$B$91 -> 16000 | T19: =(I19+J19)*'Premissas Precept'!$B$17 -> 3499.25 | U19: =(I19+J19)*'Premissas Precept'!$B$18 -> 24494.75 | V19: =D19*'Premissas Precept'!$B$19+E19*'Premissas Precept'!$B$20 -> 3600 | W19: =SUM(O19:V19) -> 150698.24 | X19: ='Premissas Precept'!$B$42 -> 12000 | Y19: =IF(A19>='Premissas Precept'!$B$47,'Premissas Precept'!$B$48*K19,0) -> 80229.905 | Z19: =X19+Y19 -> 92229.905 | AA19: =K19-W19-Z19 -> 84540.855 | AB19: =Y19/'Premissas Precept'!$B$45 -> 11461.415 | AC19: =IF(AA19>=0,"Sim","Não") -> Sim
A20: 15 | B20: =ROUND($B$9*(1+'Premissas Precept'!$B$88)^(A20-4),0) -> 17 | C20: =C19-ROUND(C19*'Premissas Precept'!$B$89,0)+B20 -> 149 | D20: 4 | E20: 1 | F20: =D20*'Premissas Precept'!$B$92+SUMPRODUCT(($A$6:$A$29>A20-'Premissas Precept'!$B$93)*($A$6:$A$29<=A20)*$E$6:$E$29) -> 7 | G20: =MAX(0,C20-F20) -> 142 | H20: =G20*'Premissas Precept'!$B$8 -> 283432 | I20: =D20*'Premissas Precept'!$B$9 -> 39988 | J20: =E20*'Premissas Precept'!$B$10 -> 29997 | K20: =H20+I20+J20 -> 353417 | L20: =SUM(K8:K19) -> 2052553 | M20: =IF(L20<='Premissas Precept'!$B$96,"Simples","Presumido") -> Simples | N20: =IF(M20="Simples",IF(L20<=0,'Premissas Precept'!$C$24,(L20*LOOKUP(L20,'Premissas Precept'!$B$24:$B$29,'Premissas Precept'!$C$24:$C$29)-LOOKUP(L20,'Premissas Precept'!$B$24:$B$29,'Premissas Precept'!$D$24:$D$29))/L20)+IF(L20>'Premissas Precept'!$B$102,'Premissas Precept'!$B$101,0),(('Premissas Precept'!$B$98+'Premissas Precept'!$B$99)*'Premissas Precept'!$B$97*K20+0.1*MAX(0,'Premissas Precept'!$B$97*K20-20000)+('Premissas Precept'!$B$100+'Premissas Precept'!$B$101)*K20)/K20) -> 0.199745 | O20: =K20*N20 -> 70593.277 | P20: =C20*'Premissas Precept'!$B$15 -> 13410 | Q20: =C20*'Premissas Precept'!$B$90 -> 22350 | R20: =K20*'Premissas Precept'!$B$16 -> 7068.34 | S20: =B20*'Premissas Precept'!$B$91 -> 17000 | T20: =(I20+J20)*'Premissas Precept'!$B$17 -> 3499.25 | U20: =(I20+J20)*'Premissas Precept'!$B$18 -> 24494.75 | V20: =D20*'Premissas Precept'!$B$19+E20*'Premissas Precept'!$B$20 -> 3600 | W20: =SUM(O20:V20) -> 162015.62 | X20: ='Premissas Precept'!$B$42 -> 12000 | Y20: =IF(A20>='Premissas Precept'!$B$47,'Premissas Precept'!$B$48*K20,0) -> 86587.165 | Z20: =X20+Y20 -> 98587.165 | AA20: =K20-W20-Z20 -> 92814.218 | AB20: =Y20/'Premissas Precept'!$B$45 -> 12369.595 | AC20: =IF(AA20>=0,"Sim","Não") -> Sim
A21: 16 | B21: =ROUND($B$9*(1+'Premissas Precept'!$B$88)^(A21-4),0) -> 18 | C21: =C20-ROUND(C20*'Premissas Precept'!$B$89,0)+B21 -> 163 | D21: 4 | E21: 1 | F21: =D21*'Premissas Precept'!$B$92+SUMPRODUCT(($A$6:$A$29>A21-'Premissas Precept'!$B$93)*($A$6:$A$29<=A21)*$E$6:$E$29) -> 7 | G21: =MAX(0,C21-F21) -> 156 | H21: =G21*'Premissas Precept'!$B$8 -> 311376 | I21: =D21*'Premissas Precept'!$B$9 -> 39988 | J21: =E21*'Premissas Precept'!$B$10 -> 29997 | K21: =H21+I21+J21 -> 381361 | L21: =SUM(K9:K20) -> 2376030 | M21: =IF(L21<='Premissas Precept'!$B$96,"Simples","Presumido") -> Simples | N21: =IF(M21="Simples",IF(L21<=0,'Premissas Precept'!$C$24,(L21*LOOKUP(L21,'Premissas Precept'!$B$24:$B$29,'Premissas Precept'!$C$24:$C$29)-LOOKUP(L21,'Premissas Precept'!$B$24:$B$29,'Premissas Precept'!$D$24:$D$29))/L21)+IF(L21>'Premissas Precept'!$B$102,'Premissas Precept'!$B$101,0),(('Premissas Precept'!$B$98+'Premissas Precept'!$B$99)*'Premissas Precept'!$B$97*K21+0.1*MAX(0,'Premissas Precept'!$B$97*K21-20000)+('Premissas Precept'!$B$100+'Premissas Precept'!$B$101)*K21)/K21) -> 0.20386397 | O21: =K21*N21 -> 77745.766 | P21: =C21*'Premissas Precept'!$B$15 -> 14670 | Q21: =C21*'Premissas Precept'!$B$90 -> 24450 | R21: =K21*'Premissas Precept'!$B$16 -> 7627.22 | S21: =B21*'Premissas Precept'!$B$91 -> 18000 | T21: =(I21+J21)*'Premissas Precept'!$B$17 -> 3499.25 | U21: =(I21+J21)*'Premissas Precept'!$B$18 -> 24494.75 | V21: =D21*'Premissas Precept'!$B$19+E21*'Premissas Precept'!$B$20 -> 3600 | W21: =SUM(O21:V21) -> 174086.99 | X21: ='Premissas Precept'!$B$42 -> 12000 | Y21: =IF(A21>='Premissas Precept'!$B$47,'Premissas Precept'!$B$48*K21,0) -> 93433.445 | Z21: =X21+Y21 -> 105433.45 | AA21: =K21-W21-Z21 -> 101840.57 | AB21: =Y21/'Premissas Precept'!$B$45 -> 13347.635 | AC21: =IF(AA21>=0,"Sim","Não") -> Sim
A22: 17 | B22: =ROUND($B$9*(1+'Premissas Precept'!$B$88)^(A22-4),0) -> 19 | C22: =C21-ROUND(C21*'Premissas Precept'!$B$89,0)+B22 -> 177 | D22: 4 | E22: 1 | F22: =D22*'Premissas Precept'!$B$92+SUMPRODUCT(($A$6:$A$29>A22-'Premissas Precept'!$B$93)*($A$6:$A$29<=A22)*$E$6:$E$29) -> 7 | G22: =MAX(0,C22-F22) -> 170 | H22: =G22*'Premissas Precept'!$B$8 -> 339320 | I22: =D22*'Premissas Precept'!$B$9 -> 39988 | J22: =E22*'Premissas Precept'!$B$10 -> 29997 | K22: =H22+I22+J22 -> 409305 | L22: =SUM(K10:K21) -> 2699490 | M22: =IF(L22<='Premissas Precept'!$B$96,"Simples","Presumido") -> Simples | N22: =IF(M22="Simples",IF(L22<=0,'Premissas Precept'!$C$24,(L22*LOOKUP(L22,'Premissas Precept'!$B$24:$B$29,'Premissas Precept'!$C$24:$C$29)-LOOKUP(L22,'Premissas Precept'!$B$24:$B$29,'Premissas Precept'!$D$24:$D$29))/L22)+IF(L22>'Premissas Precept'!$B$102,'Premissas Precept'!$B$101,0),(('Premissas Precept'!$B$98+'Premissas Precept'!$B$99)*'Premissas Precept'!$B$97*K22+0.1*MAX(0,'Premissas Precept'!$B$97*K22-20000)+('Premissas Precept'!$B$100+'Premissas Precept'!$B$101)*K22)/K22) -> 0.20699565 | O22: =K22*N22 -> 84724.356 | P22: =C22*'Premissas Precept'!$B$15 -> 15930 | Q22: =C22*'Premissas Precept'!$B$90 -> 26550 | R22: =K22*'Premissas Precept'!$B$16 -> 8186.1 | S22: =B22*'Premissas Precept'!$B$91 -> 19000 | T22: =(I22+J22)*'Premissas Precept'!$B$17 -> 3499.25 | U22: =(I22+J22)*'Premissas Precept'!$B$18 -> 24494.75 | V22: =D22*'Premissas Precept'!$B$19+E22*'Premissas Precept'!$B$20 -> 3600 | W22: =SUM(O22:V22) -> 185984.46 | X22: ='Premissas Precept'!$B$42 -> 12000 | Y22: =IF(A22>='Premissas Precept'!$B$47,'Premissas Precept'!$B$48*K22,0) -> 100279.73 | Z22: =X22+Y22 -> 112279.73 | AA22: =K22-W22-Z22 -> 111040.82 | AB22: =Y22/'Premissas Precept'!$B$45 -> 14325.675 | AC22: =IF(AA22>=0,"Sim","Não") -> Sim
A23: 18 | B23: =ROUND($B$9*(1+'Premissas Precept'!$B$88)^(A23-4),0) -> 20 | C23: =C22-ROUND(C22*'Premissas Precept'!$B$89,0)+B23 -> 192 | D23: 4 | E23: 1 | F23: =D23*'Premissas Precept'!$B$92+SUMPRODUCT(($A$6:$A$29>A23-'Premissas Precept'!$B$93)*($A$6:$A$29<=A23)*$E$6:$E$29) -> 7 | G23: =MAX(0,C23-F23) -> 185 | H23: =G23*'Premissas Precept'!$B$8 -> 369260 | I23: =D23*'Premissas Precept'!$B$9 -> 39988 | J23: =E23*'Premissas Precept'!$B$10 -> 29997 | K23: =H23+I23+J23 -> 439245 | L23: =SUM(K11:K22) -> 3030934 | M23: =IF(L23<='Premissas Precept'!$B$96,"Simples","Presumido") -> Simples | N23: =IF(M23="Simples",IF(L23<=0,'Premissas Precept'!$C$24,(L23*LOOKUP(L23,'Premissas Precept'!$B$24:$B$29,'Premissas Precept'!$C$24:$C$29)-LOOKUP(L23,'Premissas Precept'!$B$24:$B$29,'Premissas Precept'!$D$24:$D$29))/L23)+IF(L23>'Premissas Precept'!$B$102,'Premissas Precept'!$B$101,0),(('Premissas Precept'!$B$98+'Premissas Precept'!$B$99)*'Premissas Precept'!$B$97*K23+0.1*MAX(0,'Premissas Precept'!$B$97*K23-20000)+('Premissas Precept'!$B$100+'Premissas Precept'!$B$101)*K23)/K23) -> 0.20951127 | O23: =K23*N23 -> 92026.776 | P23: =C23*'Premissas Precept'!$B$15 -> 17280 | Q23: =C23*'Premissas Precept'!$B$90 -> 28800 | R23: =K23*'Premissas Precept'!$B$16 -> 8784.9 | S23: =B23*'Premissas Precept'!$B$91 -> 20000 | T23: =(I23+J23)*'Premissas Precept'!$B$17 -> 3499.25 | U23: =(I23+J23)*'Premissas Precept'!$B$18 -> 24494.75 | V23: =D23*'Premissas Precept'!$B$19+E23*'Premissas Precept'!$B$20 -> 3600 | W23: =SUM(O23:V23) -> 198485.68 | X23: ='Premissas Precept'!$B$42 -> 12000 | Y23: =IF(A23>='Premissas Precept'!$B$47,'Premissas Precept'!$B$48*K23,0) -> 107615.02 | Z23: =X23+Y23 -> 119615.02 | AA23: =K23-W23-Z23 -> 121144.3 | AB23: =Y23/'Premissas Precept'!$B$45 -> 15373.575 | AC23: =IF(AA23>=0,"Sim","Não") -> Sim
A24: 19 | B24: =ROUND($B$9*(1+'Premissas Precept'!$B$88)^(A24-4),0) -> 21 | C24: =C23-ROUND(C23*'Premissas Precept'!$B$89,0)+B24 -> 207 | D24: 5 | E24: 1 | F24: =D24*'Premissas Precept'!$B$92+SUMPRODUCT(($A$6:$A$29>A24-'Premissas Precept'!$B$93)*($A$6:$A$29<=A24)*$E$6:$E$29) -> 8 | G24: =MAX(0,C24-F24) -> 199 | H24: =G24*'Premissas Precept'!$B$8 -> 397204 | I24: =D24*'Premissas Precept'!$B$9 -> 49985 | J24: =E24*'Premissas Precept'!$B$10 -> 29997 | K24: =H24+I24+J24 -> 477186 | L24: =SUM(K12:K23) -> 3344357 | M24: =IF(L24<='Premissas Precept'!$B$96,"Simples","Presumido") -> Simples | N24: =IF(M24="Simples",IF(L24<=0,'Premissas Precept'!$C$24,(L24*LOOKUP(L24,'Premissas Precept'!$B$24:$B$29,'Premissas Precept'!$C$24:$C$29)-LOOKUP(L24,'Premissas Precept'!$B$24:$B$29,'Premissas Precept'!$D$24:$D$29))/L24)+IF(L24>'Premissas Precept'!$B$102,'Premissas Precept'!$B$101,0),(('Premissas Precept'!$B$98+'Premissas Precept'!$B$99)*'Premissas Precept'!$B$97*K24+0.1*MAX(0,'Premissas Precept'!$B$97*K24-20000)+('Premissas Precept'!$B$100+'Premissas Precept'!$B$101)*K24)/K24) -> 0.21143141 | O24: =K24*N24 -> 100892.11 | P24: =C24*'Premissas Precept'!$B$15 -> 18630 | Q24: =C24*'Premissas Precept'!$B$90 -> 31050 | R24: =K24*'Premissas Precept'!$B$16 -> 9543.72 | S24: =B24*'Premissas Precept'!$B$91 -> 21000 | T24: =(I24+J24)*'Premissas Precept'!$B$17 -> 3999.1 | U24: =(I24+J24)*'Premissas Precept'!$B$18 -> 27993.7 | V24: =D24*'Premissas Precept'!$B$19+E24*'Premissas Precept'!$B$20 -> 4200 | W24: =SUM(O24:V24) -> 217308.63 | X24: ='Premissas Precept'!$B$42 -> 12000 | Y24: =IF(A24>='Premissas Precept'!$B$47,'Premissas Precept'!$B$48*K24,0) -> 116910.57 | Z24: =X24+Y24 -> 128910.57 | AA24: =K24-W24-Z24 -> 130966.8 | AB24: =Y24/'Premissas Precept'!$B$45 -> 16701.51 | AC24: =IF(AA24>=0,"Sim","Não") -> Sim
A25: 20 | B25: =ROUND($B$9*(1+'Premissas Precept'!$B$88)^(A25-4),0) -> 22 | C25: =C24-ROUND(C24*'Premissas Precept'!$B$89,0)+B25 -> 223 | D25: 5 | E25: 1 | F25: =D25*'Premissas Precept'!$B$92+SUMPRODUCT(($A$6:$A$29>A25-'Premissas Precept'!$B$93)*($A$6:$A$29<=A25)*$E$6:$E$29) -> 8 | G25: =MAX(0,C25-F25) -> 215 | H25: =G25*'Premissas Precept'!$B$8 -> 429140 | I25: =D25*'Premissas Precept'!$B$9 -> 49985 | J25: =E25*'Premissas Precept'!$B$10 -> 29997 | K25: =H25+I25+J25 -> 509122 | L25: =SUM(K13:K24) -> 3703762 | M25: =IF(L25<='Premissas Precept'!$B$96,"Simples","Presumido") -> Simples | N25: =IF(M25="Simples",IF(L25<=0,'Premissas Precept'!$C$24,(L25*LOOKUP(L25,'Premissas Precept'!$B$24:$B$29,'Premissas Precept'!$C$24:$C$29)-LOOKUP(L25,'Premissas Precept'!$B$24:$B$29,'Premissas Precept'!$D$24:$D$29))/L25)+IF(L25>'Premissas Precept'!$B$102,'Premissas Precept'!$B$101,0),(('Premissas Precept'!$B$98+'Premissas Precept'!$B$99)*'Premissas Precept'!$B$97*K25+0.1*MAX(0,'Premissas Precept'!$B$97*K25-20000)+('Premissas Precept'!$B$100+'Premissas Precept'!$B$101)*K25)/K25) -> 0.20920229 | O25: =K25*N25 -> 106509.49 | P25: =C25*'Premissas Precept'!$B$15 -> 20070 | Q25: =C25*'Premissas Precept'!$B$90 -> 33450 | R25: =K25*'Premissas Precept'!$B$16 -> 10182.44 | S25: =B25*'Premissas Precept'!$B$91 -> 22000 | T25: =(I25+J25)*'Premissas Precept'!$B$17 -> 3999.1 | U25: =(I25+J25)*'Premissas Precept'!$B$18 -> 27993.7 | V25: =D25*'Premissas Precept'!$B$19+E25*'Premissas Precept'!$B$20 -> 4200 | W25: =SUM(O25:V25) -> 228404.73 | X25: ='Premissas Precept'!$B$42 -> 12000 | Y25: =IF(A25>='Premissas Precept'!$B$47,'Premissas Precept'!$B$48*K25,0) -> 124734.89 | Z25: =X25+Y25 -> 136734.89 | AA25: =K25-W25-Z25 -> 143982.38 | AB25: =Y25/'Premissas Precept'!$B$45 -> 17819.27 | AC25: =IF(AA25>=0,"Sim","Não") -> Sim
A26: 21 | B26: =ROUND($B$9*(1+'Premissas Precept'!$B$88)^(A26-4),0) -> 23 | C26: =C25-ROUND(C25*'Premissas Precept'!$B$89,0)+B26 -> 239 | D26: 5 | E26: 1 | F26: =D26*'Premissas Precept'!$B$92+SUMPRODUCT(($A$6:$A$29>A26-'Premissas Precept'!$B$93)*($A$6:$A$29<=A26)*$E$6:$E$29) -> 8 | G26: =MAX(0,C26-F26) -> 231 | H26: =G26*'Premissas Precept'!$B$8 -> 461076 | I26: =D26*'Premissas Precept'!$B$9 -> 49985 | J26: =E26*'Premissas Precept'!$B$10 -> 29997 | K26: =H26+I26+J26 -> 541058 | L26: =SUM(K14:K25) -> 4047142 | M26: =IF(L26<='Premissas Precept'!$B$96,"Simples","Presumido") -> Simples | N26: =IF(M26="Simples",IF(L26<=0,'Premissas Precept'!$C$24,(L26*LOOKUP(L26,'Premissas Precept'!$B$24:$B$29,'Premissas Precept'!$C$24:$C$29)-LOOKUP(L26,'Premissas Precept'!$B$24:$B$29,'Premissas Precept'!$D$24:$D$29))/L26)+IF(L26>'Premissas Precept'!$B$102,'Premissas Precept'!$B$101,0),(('Premissas Precept'!$B$98+'Premissas Precept'!$B$99)*'Premissas Precept'!$B$97*K26+0.1*MAX(0,'Premissas Precept'!$B$97*K26-20000)+('Premissas Precept'!$B$100+'Premissas Precept'!$B$101)*K26)/K26) -> 0.22157251 | O26: =K26*N26 -> 119883.58 | P26: =C26*'Premissas Precept'!$B$15 -> 21510 | Q26: =C26*'Premissas Precept'!$B$90 -> 35850 | R26: =K26*'Premissas Precept'!$B$16 -> 10821.16 | S26: =B26*'Premissas Precept'!$B$91 -> 23000 | T26: =(I26+J26)*'Premissas Precept'!$B$17 -> 3999.1 | U26: =(I26+J26)*'Premissas Precept'!$B$18 -> 27993.7 | V26: =D26*'Premissas Precept'!$B$19+E26*'Premissas Precept'!$B$20 -> 4200 | W26: =SUM(O26:V26) -> 247257.54 | X26: ='Premissas Precept'!$B$42 -> 12000 | Y26: =IF(A26>='Premissas Precept'!$B$47,'Premissas Precept'!$B$48*K26,0) -> 132559.21 | Z26: =X26+Y26 -> 144559.21 | AA26: =K26-W26-Z26 -> 149241.25 | AB26: =Y26/'Premissas Precept'!$B$45 -> 18937.03 | AC26: =IF(AA26>=0,"Sim","Não") -> Sim
A27: 22 | B27: =ROUND($B$9*(1+'Premissas Precept'!$B$88)^(A27-4),0) -> 24 | C27: =C26-ROUND(C26*'Premissas Precept'!$B$89,0)+B27 -> 256 | D27: 5 | E27: 1 | F27: =D27*'Premissas Precept'!$B$92+SUMPRODUCT(($A$6:$A$29>A27-'Premissas Precept'!$B$93)*($A$6:$A$29<=A27)*$E$6:$E$29) -> 8 | G27: =MAX(0,C27-F27) -> 248 | H27: =G27*'Premissas Precept'!$B$8 -> 495008 | I27: =D27*'Premissas Precept'!$B$9 -> 49985 | J27: =E27*'Premissas Precept'!$B$10 -> 29997 | K27: =H27+I27+J27 -> 574990 | L27: =SUM(K15:K26) -> 4420502 | M27: =IF(L27<='Premissas Precept'!$B$96,"Simples","Presumido") -> Simples | N27: =IF(M27="Simples",IF(L27<=0,'Premissas Precept'!$C$24,(L27*LOOKUP(L27,'Premissas Precept'!$B$24:$B$29,'Premissas Precept'!$C$24:$C$29)-LOOKUP(L27,'Premissas Precept'!$B$24:$B$29,'Premissas Precept'!$D$24:$D$29))/L27)+IF(L27>'Premissas Precept'!$B$102,'Premissas Precept'!$B$101,0),(('Premissas Precept'!$B$98+'Premissas Precept'!$B$99)*'Premissas Precept'!$B$97*K27+0.1*MAX(0,'Premissas Precept'!$B$97*K27-20000)+('Premissas Precept'!$B$100+'Premissas Precept'!$B$101)*K27)/K27) -> 0.23284193 | O27: =K27*N27 -> 133881.78 | P27: =C27*'Premissas Precept'!$B$15 -> 23040 | Q27: =C27*'Premissas Precept'!$B$90 -> 38400 | R27: =K27*'Premissas Precept'!$B$16 -> 11499.8 | S27: =B27*'Premissas Precept'!$B$91 -> 24000 | T27: =(I27+J27)*'Premissas Precept'!$B$17 -> 3999.1 | U27: =(I27+J27)*'Premissas Precept'!$B$18 -> 27993.7 | V27: =D27*'Premissas Precept'!$B$19+E27*'Premissas Precept'!$B$20 -> 4200 | W27: =SUM(O27:V27) -> 267014.38 | X27: ='Premissas Precept'!$B$42 -> 12000 | Y27: =IF(A27>='Premissas Precept'!$B$47,'Premissas Precept'!$B$48*K27,0) -> 140872.55 | Z27: =X27+Y27 -> 152872.55 | AA27: =K27-W27-Z27 -> 155103.07 | AB27: =Y27/'Premissas Precept'!$B$45 -> 20124.65 | AC27: =IF(AA27>=0,"Sim","Não") -> Sim
A28: 23 | B28: =ROUND($B$9*(1+'Premissas Precept'!$B$88)^(A28-4),0) -> 25 | C28: =C27-ROUND(C27*'Premissas Precept'!$B$89,0)+B28 -> 273 | D28: 5 | E28: 0 | F28: =D28*'Premissas Precept'!$B$92+SUMPRODUCT(($A$6:$A$29>A28-'Premissas Precept'!$B$93)*($A$6:$A$29<=A28)*$E$6:$E$29) -> 7 | G28: =MAX(0,C28-F28) -> 266 | H28: =G28*'Premissas Precept'!$B$8 -> 530936 | I28: =D28*'Premissas Precept'!$B$9 -> 49985 | J28: =E28*'Premissas Precept'!$B$10 -> 0 | K28: =H28+I28+J28 -> 580921 | L28: =SUM(K16:K27) -> 4785838 | M28: =IF(L28<='Premissas Precept'!$B$96,"Simples","Presumido") -> Simples | N28: =IF(M28="Simples",IF(L28<=0,'Premissas Precept'!$C$24,(L28*LOOKUP(L28,'Premissas Precept'!$B$24:$B$29,'Premissas Precept'!$C$24:$C$29)-LOOKUP(L28,'Premissas Precept'!$B$24:$B$29,'Premissas Precept'!$D$24:$D$29))/L28)+IF(L28>'Premissas Precept'!$B$102,'Premissas Precept'!$B$101,0),(('Premissas Precept'!$B$98+'Premissas Precept'!$B$99)*'Premissas Precept'!$B$97*K28+0.1*MAX(0,'Premissas Precept'!$B$97*K28-20000)+('Premissas Precept'!$B$100+'Premissas Precept'!$B$101)*K28)/K28) -> 0.2421671 | O28: =K28*N28 -> 140679.95 | P28: =C28*'Premissas Precept'!$B$15 -> 24570 | Q28: =C28*'Premissas Precept'!$B$90 -> 40950 | R28: =K28*'Premissas Precept'!$B$16 -> 11618.42 | S28: =B28*'Premissas Precept'!$B$91 -> 25000 | T28: =(I28+J28)*'Premissas Precept'!$B$17 -> 2499.25 | U28: =(I28+J28)*'Premissas Precept'!$B$18 -> 17494.75 | V28: =D28*'Premissas Precept'!$B$19+E28*'Premissas Precept'!$B$20 -> 3000 | W28: =SUM(O28:V28) -> 265812.37 | X28: ='Premissas Precept'!$B$42 -> 12000 | Y28: =IF(A28>='Premissas Precept'!$B$47,'Premissas Precept'!$B$48*K28,0) -> 142325.64 | Z28: =X28+Y28 -> 154325.64 | AA28: =K28-W28-Z28 -> 160782.98 | AB28: =Y28/'Premissas Precept'!$B$45 -> 20332.235 | AC28: =IF(AA28>=0,"Sim","Não") -> Sim
A29: 24 | B29: =ROUND($B$9*(1+'Premissas Precept'!$B$88)^(A29-4),0) -> 27 | C29: =C28-ROUND(C28*'Premissas Precept'!$B$89,0)+B29 -> 292 | D29: 5 | E29: 1 | F29: =D29*'Premissas Precept'!$B$92+SUMPRODUCT(($A$6:$A$29>A29-'Premissas Precept'!$B$93)*($A$6:$A$29<=A29)*$E$6:$E$29) -> 7 | G29: =MAX(0,C29-F29) -> 285 | H29: =G29*'Premissas Precept'!$B$8 -> 568860 | I29: =D29*'Premissas Precept'!$B$9 -> 49985 | J29: =E29*'Premissas Precept'!$B$10 -> 29997 | K29: =H29+I29+J29 -> 648842 | L29: =SUM(K17:K28) -> 5155149 | M29: =IF(L29<='Premissas Precept'!$B$96,"Simples","Presumido") -> Presumido | N29: =IF(M29="Simples",IF(L29<=0,'Premissas Precept'!$C$24,(L29*LOOKUP(L29,'Premissas Precept'!$B$24:$B$29,'Premissas Precept'!$C$24:$C$29)-LOOKUP(L29,'Premissas Precept'!$B$24:$B$29,'Premissas Precept'!$D$24:$D$29))/L29)+IF(L29>'Premissas Precept'!$B$102,'Premissas Precept'!$B$101,0),(('Premissas Precept'!$B$98+'Premissas Precept'!$B$99)*'Premissas Precept'!$B$97*K29+0.1*MAX(0,'Premissas Precept'!$B$97*K29-20000)+('Premissas Precept'!$B$100+'Premissas Precept'!$B$101)*K29)/K29) -> 0.19221759 | O29: =K29*N29 -> 124718.84 | P29: =C29*'Premissas Precept'!$B$15 -> 26280 | Q29: =C29*'Premissas Precept'!$B$90 -> 43800 | R29: =K29*'Premissas Precept'!$B$16 -> 12976.84 | S29: =B29*'Premissas Precept'!$B$91 -> 27000 | T29: =(I29+J29)*'Premissas Precept'!$B$17 -> 3999.1 | U29: =(I29+J29)*'Premissas Precept'!$B$18 -> 27993.7 | V29: =D29*'Premissas Precept'!$B$19+E29*'Premissas Precept'!$B$20 -> 4200 | W29: =SUM(O29:V29) -> 270968.48 | X29: ='Premissas Precept'!$B$42 -> 12000 | Y29: =IF(A29>='Premissas Precept'!$B$47,'Premissas Precept'!$B$48*K29,0) -> 158966.29 | Z29: =X29+Y29 -> 170966.29 | AA29: =K29-W29-Z29 -> 206907.23 | AB29: =Y29/'Premissas Precept'!$B$45 -> 22709.47 | AC29: =IF(AA29>=0,"Sim","Não") -> Sim
A30: TOTAL | B30: =SUM(B6:B29) -> 374 | D30: =SUM(D6:D29) -> 65 | E30: =SUM(E6:E29) -> 15 | H30: =SUM(H6:H29) -> 5890196 | I30: =SUM(I6:I29) -> 649805 | J30: =SUM(J6:J29) -> 449955 | K30: =SUM(K6:K29) -> 6989956 | O30: =SUM(O6:O29) -> 1437695.9 | P30: =SUM(P6:P29) -> 275310 | Q30: =SUM(Q6:Q29) -> 458850 | R30: =SUM(R6:R29) -> 139799.12 | S30: =SUM(S6:S29) -> 374000 | T30: =SUM(T6:T29) -> 54988 | U30: =SUM(U6:U29) -> 384916 | V30: =SUM(V6:V29) -> 57000 | ... AB30: =SUM(AB6:AB29) -> 242832.1
A32: RESUMO POR FASE → seção 5 da ficha (médias mensais de cada fase)
A33: Fase | C33: Períodos | E33: Vendas Brutas por mês (R$) | F33: Despesas Variáveis por mês (R$) | G33: Despesas Fixas por mês (R$) | H33: Investimentos (R$) | I33: % variável da fase | J33: Resultado por mês (R$) | K33: Clientes Core ativos (média) | L33: Sprints na fase | M33: Scales na fase
A34: Antes de abrir | C34: 0 | E34: 0 | F34: 0 | G34: 0 | H34: ='Premissas Precept'!B58 -> 102000
A35: Início | C35: 1 a 6 | E35: =AVERAGE(K6:K11) -> 52246.667 | F35: =AVERAGE(W6:W11) -> 27272.749 | G35: =AVERAGE(Z6:Z11) -> 22681.347 | H35: 0 | I35: =F35/E35 -> 0.5219998 | J35: =E35-F35-G35 -> 2292.5706 | K35: =AVERAGE(C6:C11) -> 21.833333 | L35: =SUM(D6:D11) -> 3 | M35: =SUM(E6:E11) -> 1
A36: Crescimento | C36: 7 a 12 | E36: =AVERAGE(K12:K17) -> 188007.83 | F36: =AVERAGE(W12:W17) -> 84735.858 | G36: =AVERAGE(Z12:Z17) -> 58061.919 | H36: 0 | I36: =F36/E36 -> 0.45070387 | J36: =E36-F36-G36 -> 45210.056 | K36: =AVERAGE(C12:C17) -> 82.833333 | L36: =SUM(D12:D17) -> 8 | M36: =SUM(E12:E17) -> 3
A37: Estabilidade | C37: 13 a 24 | E37: =AVERAGE(K18:K29) -> 462369.08 | F37: =AVERAGE(W18:W29) -> 209208.95 | G37: =AVERAGE(Z18:Z29) -> 125280.43 | H37: 0 | I37: =F37/E37 -> 0.45247176 | J37: =E37-F37-G37 -> 127879.71 | K37: =AVERAGE(C18:C29) -> 202.58333 | L37: =SUM(D18:D29) -> 54 | M37: =SUM(E18:E29) -> 11
A40: MÊS TÍPICO (média da Estabilidade, meses 13 a 24) → seções 1, 2 e 3 da ficha
A41: Item | E41: Quantidade por mês | F41: Preço ou base (R$) | G41: Valor mensal (R$)
A42: Core – assinatura mensal (clientes pagantes) | E42: =AVERAGE(G18:G29) -> 195.33333 | F42: ='Premissas Precept'!B8 -> 1996 | G42: =E42*F42 -> 389885.33
A43: Sprint – planejamento de 7 dias | E43: =AVERAGE(D18:D29) -> 4.5 | F43: ='Premissas Precept'!B9 -> 9997 | G43: =E43*F43 -> 44986.5
A44: Scale – implementação de 6 meses | E44: =AVERAGE(E18:E29) -> 0.91666667 | F44: ='Premissas Precept'!B10 -> 29997 | G44: =E44*F44 -> 27497.25
A45: TOTAL DA RECEITA MENSAL (A) | G45: =SUM(G42:G44) -> 462369.08
A46: Tokens de IA e nuvem (por cliente ativo) | E46: =AVERAGE(C18:C29) -> 202.58333 | F46: ='Premissas Precept'!B15 -> 90 | G46: =AVERAGE(P18:P29) -> 18232.5
A47: Suporte e sucesso do cliente (por cliente ativo) | E47: =AVERAGE(C18:C29) -> 202.58333 | F47: ='Premissas Precept'!B90 -> 150 | G47: =AVERAGE(Q18:Q29) -> 30387.5
A48: Impostos (Simples ou Lucro Presumido) | F48: =G48/G45 -> 0.21169539 | G48: =AVERAGE(O18:O29) -> 97881.402
A49: Meio de pagamento | F49: ='Premissas Precept'!B16 -> 0.02 | G49: =AVERAGE(R18:R29) -> 9247.3817
A50: Aquisição de clientes Core (por cliente novo) | E50: =AVERAGE(B18:B29) -> 20.666667 | F50: ='Premissas Precept'!B91 -> 1000 | G50: =AVERAGE(S18:S29) -> 20666.667
A51: Comissões de parceiros (Sprint e Scale) | F51: ='Premissas Precept'!B17 -> 0.05 | G51: =AVERAGE(T18:T29) -> 3624.1875
A52: Deslocamento (Sprint e Scale) | G52: =AVERAGE(V18:V29) -> 3800
A53: Especialistas na entrega | F53: ='Premissas Precept'!B18 -> 0.35 | G53: =AVERAGE(U18:U29) -> 25369.312
A54: TOTAL DAS DESPESAS VARIÁVEIS (B) | F54: =G54/G45 -> 0.45247176 | G54: =SUM(G46:G53) -> 209208.95
A55: Retirada dos sócios (7 sócios × % da receita) | F55: ='Premissas Precept'!B48 -> 0.245 | G55: =AVERAGE(Y18:Y29) -> 113280.43
A56: Despesas fixas sem retirada | G56: ='Premissas Precept'!B42 -> 12000
A57: TOTAL DAS DESPESAS FIXAS (C) | G57: =G55+G56 -> 125280.43

Sheet Mercado TAM SAM SOM
A1: MERCADO DA PRECEPT – TAM, SAM, BEACHHEAD E SOM
A2: Cálculo de baixo para cima a partir do número de advogados. Cinza = dado com fonte ou hipótese declarada (veja a coluna C). Azul = automático.
A4: 1. DADOS DE ENTRADA
A5: Advogados inscritos na OAB no Brasil | B5: 1300000 | C5: Fonte: “o Brasil conta com mais de 1,3 milhão de advogados” (Migalhas, Sociedades de advogados: profissionalização e papel da OAB; OAB Nacional, 2025).
A6: % dos advogados que atuam em escritórios de R$ 1 a 10 mi/ano | B6: 0.12 | C6: HIPÓTESE a validar. A maioria atua sozinha ou em sociedades pequenas; em 2015 já havia mais de 35 mil sociedades de advogados (OAB/Migalhas).
A7: Advogados por escritório nessa faixa (média) | B7: 10 | C7: HIPÓTESE: faixa do ICP de 4 a 40 advogados, com faturamento de R$ 150 a 300 mil por advogado ao ano.
A8: % dos advogados no estado de São Paulo | B8: 0.25 | C8: HIPÓTESE a confirmar no Quadro de Advogados da OAB. Em 2025 a OAB SP teve alta de 12% nos registros de sociedades (Jornal da Advocacia OAB SP).
A9: % do estado concentrado na Grande São Paulo | B9: 0.7 | C9: HIPÓTESE: capital e região metropolitana concentram a maior parte da advocacia paulista.
A10: % de escritórios com foco em direito previdenciário | B10: 0.2 | C10: HIPÓTESE: o previdenciário é uma das maiores áreas de volume da advocacia (litígios contra o INSS).
A11: Receita anual por cliente do Core (R$/ano) | B11: =12*'Premissas Precept'!B8 -> 23952 | C11: Assinatura do Core × 12 meses. Sprint e Scale ficam de fora do tamanho de mercado (receita pontual).
A13: 2. TAMANHO DO MERCADO
A14: Camada | B14: Escritórios | C14: Receita potencial do Core (R$/ano) | D14: Definição
A15: TAM – escritórios de R$ 1 a 10 mi/ano no Brasil | B15: =ROUND(B5*B6/B7,0) -> 15600 | C15: =B15*$B$11 -> 373651200 | D15: Todos os escritórios do perfil do ICP no país, de qualquer área do direito.
A16: SAM – mesmo perfil no estado de São Paulo | B16: =ROUND(B15*B8,0) -> 3900 | C16: =B16*$B$11 -> 93412800 | D16: Onde a Precept consegue vender e entregar Sprint e Scale presencialmente nos 2 primeiros anos.
A17: Beachhead – previdenciário na Grande São Paulo | B17: =ROUND(B16*B9*B10,0) -> 546 | C17: =B17*$B$11 -> 13077792 | D17: Mercado inicial: compram software jurídico, conversam entre si (associações e eventos do setor) e têm a mesma dor de gestão.
A18: SOM – clientes Core ativos no mês 24 (modelo financeiro) | B18: ='Projeção Mensal'!C29 -> 292 | C18: ='Projeção Mensal'!G29*$B$11 -> 6826320 | D18: Receita recorrente anualizada no mês 24: clientes pagantes × assinatura × 12.
A20: 3. LEITURA DO SOM
A21: Clientes Core ativos no mês 12 | B21: ='Projeção Mensal'!C17 -> 111 | C21: No primeiro ano a venda fica concentrada no beachhead (previdenciário da Grande SP).
A22: Penetração do beachhead no mês 12 | B22: =B21/B17 -> 0.2032967
A23: SOM (mês 24) como % do SAM | B23: =B18/B16 -> 0.074871795
A24: SOM (mês 24) como % do TAM | B24: =B18/B15 -> 0.018717949
A25: SOM (mês 24) em relação ao beachhead | B25: =B18/B17 -> 0.53479853 | C25: =IF(B25>0.3,"Mais de 30% de um nicho em 2 anos é agressivo: no ano 2, parte dos clientes deve vir de fora do beachhead (outras áreas do direito em SP, como trabalhista, cível e tributário), que é o caminho de expansão do plano.","O SOM cabe com folga no beachhead.") -> Mais de 30% de um nicho em 2 anos é agressivo: no ano 2, parte dos clientes deve vir de fora do beachhead (outras áreas do direito em SP, como trabalhista, cível e tributário), que é o caminho de expansão do plano.
A27: Os dados marcados como HIPÓTESE devem ser confirmados antes da entrega: Quadro de Advogados (oab.org.br), Cadastro Nacional de Sociedades de Advogados e dados abertos do CNPJ pelo CNAE 6911-7/01 (Receita Federal). Basta trocar as células cinzas: todo o resto recalcula.

Sheet Fluxo de Caixa
A1: FLUXO DE CAIXA DETALHADO
A2: Preencha as células CINZAS. As AZUIS são calculadas. Período 0 = investimento inicial; períodos 1 a 24 = operação.
A4: Período | B4: Vendas Brutas (R$) | C4: Despesas Variáveis (R$) | D4: Despesas Fixas (R$) | E4: Resultado Operacional (R$) | F4: Investimentos (R$) | G4: Fluxo de Caixa Líquido (R$)
A5: 0 | B5: 0 | C5: 0 | D5: 0 | E5: =B5-C5-D5 -> 0 | F5: ='Premissas Precept'!B58 -> 102000 | G5: =E5-F5 -> -102000
A6: 1 | B6: ='Projeção Mensal'!K6 -> 5988 | C6: ='Projeção Mensal'!W6 -> 4767.9 | D6: ='Projeção Mensal'!Z6 -> 12000 | E6: =B6-C6-D6 -> -10779.9 | G6: =E6-F6 -> -10779.9
A7: 2 | B7: ='Projeção Mensal'!K7 -> 15968 | C7: ='Projeção Mensal'!W7 -> 9714.4 | D7: ='Projeção Mensal'!Z7 -> 12000 | E7: =B7-C7-D7 -> -5746.4 | G7: =E7-F7 -> -5746.4
A8: 3 | B8: ='Projeção Mensal'!K8 -> 29940 | C8: ='Projeção Mensal'!W8 -> 15839.5 | D8: ='Projeção Mensal'!Z8 -> 12000 | E8: =B8-C8-D8 -> 2100.5 | G8: =E8-F8 -> 2100.5
A9: 4 | B9: ='Projeção Mensal'!K9 -> 57901 | C9: ='Projeção Mensal'!W9 -> 30923.824 | D9: ='Projeção Mensal'!Z9 -> 26185.745 | E9: =B9-C9-D9 -> 791.43122 | G9: =E9-F9 -> 791.43122
A10: 5 | B10: ='Projeção Mensal'!K10 -> 77861 | C10: ='Projeção Mensal'!W10 -> 38507.296 | D10: ='Projeção Mensal'!Z10 -> 31075.945 | E10: =B10-C10-D10 -> 8277.7589 | G10: =E10-F10 -> 8277.7589
A11: 6 | B11: ='Projeção Mensal'!K11 -> 125822 | C11: ='Projeção Mensal'!W11 -> 63883.577 | D11: ='Projeção Mensal'!Z11 -> 42826.39 | E11: =B11-C11-D11 -> 19112.033 | G11: =E11-F11 -> 19112.033
A12: 7 | B12: ='Projeção Mensal'!K12 -> 117781 | C12: ='Projeção Mensal'!W12 -> 53501.896 | D12: ='Projeção Mensal'!Z12 -> 40856.345 | E12: =B12-C12-D12 -> 23422.759 | G12: =E12-F12 -> 23422.759
A13: 8 | B13: ='Projeção Mensal'!K13 -> 165742 | C13: ='Projeção Mensal'!W13 -> 79095.963 | D13: ='Projeção Mensal'!Z13 -> 52606.79 | E13: =B13-C13-D13 -> 34039.247 | G13: =E13-F13 -> 34039.247
A14: 9 | B14: ='Projeção Mensal'!K14 -> 167698 | C14: ='Projeção Mensal'!W14 -> 75207.393 | D14: ='Projeção Mensal'!Z14 -> 53086.01 | E14: =B14-C14-D14 -> 39404.597 | G14: =E14-F14 -> 39404.597
A15: 10 | B15: ='Projeção Mensal'!K15 -> 209654 | C15: ='Projeção Mensal'!W15 -> 95573.588 | D15: ='Projeção Mensal'!Z15 -> 63365.23 | E15: =B15-C15-D15 -> 50715.182 | G15: =E15-F15 -> 50715.182
A16: 11 | B16: ='Projeção Mensal'!K16 -> 211610 | C16: ='Projeção Mensal'!W16 -> 91475.041 | D16: ='Projeção Mensal'!Z16 -> 63844.45 | E16: =B16-C16-D16 -> 56290.509 | G16: =E16-F16 -> 56290.509
A17: 12 | B17: ='Projeção Mensal'!K17 -> 255562 | C17: ='Projeção Mensal'!W17 -> 113561.27 | D17: ='Projeção Mensal'!Z17 -> 74612.69 | E17: =B17-C17-D17 -> 67388.045 | G17: =E17-F17 -> 67388.045
... A29: 24 | B29: ='Projeção Mensal'!K29 -> 648842 | C29: ='Projeção Mensal'!W29 -> 270968.48 | D29: ='Projeção Mensal'!Z29 -> 170966.29 | E29: =B29-C29-D29 -> 206907.23 | G29: =E29-F29 -> 206907.23
A30: TOTAL | B30: =SUM(B5:B29) -> 6989956 | C30: =SUM(C5:C29) -> 3182559.1 | D30: =SUM(D5:D29) -> 1987824.7 | E30: =SUM(E5:E29) -> 1819572.2 | F30: =SUM(F5:F29) -> 102000 | G30: =SUM(G5:G29) -> 1717572.2
A32: Valores atuais são EXEMPLO (investimento de R$ 50.000 e lucro operacional de R$ 4.000/mês). Substitua pelos dados do seu projeto.

Sheet Necessidade de Caixa e Payback
A1: SALDO ACUMULADO, NECESSIDADE DE CAIXA E PAYBACK
A2: Aba 100% automática. Mostra quanto dinheiro o projeto acumula (ou consome) ao longo do tempo.
A4: Período | B4: Vendas Brutas (R$) | C4: Despesas Variáveis (R$) | D4: Despesas Fixas (R$) | E4: Investimentos (R$) | F4: Fluxo de Caixa Líquido (R$) | G4: Saldo Acumulado (R$) | H4: Investimento recuperado?
A5: 0 | B5: ='Fluxo de Caixa'!B5 -> 0 | C5: ='Fluxo de Caixa'!C5 -> 0 | D5: ='Fluxo de Caixa'!D5 -> 0 | E5: ='Fluxo de Caixa'!F5 -> 102000 | F5: ='Fluxo de Caixa'!G5 -> -102000 | G5: =F5 -> -102000 | H5: =IF(G5>=0,"Sim","Não") -> Não
A6: 1 | B6: ='Fluxo de Caixa'!B6 -> 5988 | C6: ='Fluxo de Caixa'!C6 -> 4767.9 | D6: ='Fluxo de Caixa'!D6 -> 12000 | E6: ='Fluxo de Caixa'!F6 -> 0 | F6: ='Fluxo de Caixa'!G6 -> -10779.9 | G6: =G5+F6 -> -112779.9 | H6: =IF(G6>=0,"Sim","Não") -> Não
A7: 2 | B7: ='Fluxo de Caixa'!B7 -> 15968 | C7: ='Fluxo de Caixa'!C7 -> 9714.4 | D7: ='Fluxo de Caixa'!D7 -> 12000 | E7: ='Fluxo de Caixa'!F7 -> 0 | F7: ='Fluxo de Caixa'!G7 -> -5746.4 | G7: =G6+F7 -> -118526.3 | H7: =IF(G7>=0,"Sim","Não") -> Não
A8: 3 | B8: ='Fluxo de Caixa'!B8 -> 29940 | C8: ='Fluxo de Caixa'!C8 -> 15839.5 | D8: ='Fluxo de Caixa'!D8 -> 12000 | E8: ='Fluxo de Caixa'!F8 -> 0 | F8: ='Fluxo de Caixa'!G8 -> 2100.5 | G8: =G7+F8 -> -116425.8 | H8: =IF(G8>=0,"Sim","Não") -> Não
A9: 4 | B9: ='Fluxo de Caixa'!B9 -> 57901 | C9: ='Fluxo de Caixa'!C9 -> 30923.824 | D9: ='Fluxo de Caixa'!D9 -> 26185.745 | E9: ='Fluxo de Caixa'!F9 -> 0 | F9: ='Fluxo de Caixa'!G9 -> 791.43122 | G9: =G8+F9 -> -115634.37 | H9: =IF(G9>=0,"Sim","Não") -> Não
A10: 5 | B10: ='Fluxo de Caixa'!B10 -> 77861 | C10: ='Fluxo de Caixa'!C10 -> 38507.296 | D10: ='Fluxo de Caixa'!D10 -> 31075.945 | E10: ='Fluxo de Caixa'!F10 -> 0 | F10: ='Fluxo de Caixa'!G10 -> 8277.7589 | G10: =G9+F10 -> -107356.61 | H10: =IF(G10>=0,"Sim","Não") -> Não
A11: 6 | B11: ='Fluxo de Caixa'!B11 -> 125822 | C11: ='Fluxo de Caixa'!C11 -> 63883.577 | D11: ='Fluxo de Caixa'!D11 -> 42826.39 | E11: ='Fluxo de Caixa'!F11 -> 0 | F11: ='Fluxo de Caixa'!G11 -> 19112.033 | G11: =G10+F11 -> -88244.576 | H11: =IF(G11>=0,"Sim","Não") -> Não
A12: 7 | B12: ='Fluxo de Caixa'!B12 -> 117781 | C12: ='Fluxo de Caixa'!C12 -> 53501.896 | D12: ='Fluxo de Caixa'!D12 -> 40856.345 | E12: ='Fluxo de Caixa'!F12 -> 0 | F12: ='Fluxo de Caixa'!G12 -> 23422.759 | G12: =G11+F12 -> -64821.818 | H12: =IF(G12>=0,"Sim","Não") -> Não
A13: 8 | B13: ='Fluxo de Caixa'!B13 -> 165742 | C13: ='Fluxo de Caixa'!C13 -> 79095.963 | D13: ='Fluxo de Caixa'!D13 -> 52606.79 | E13: ='Fluxo de Caixa'!F13 -> 0 | F13: ='Fluxo de Caixa'!G13 -> 34039.247 | G13: =G12+F13 -> -30782.571 | H13: =IF(G13>=0,"Sim","Não") -> Não
A14: 9 | B14: ='Fluxo de Caixa'!B14 -> 167698 | C14: ='Fluxo de Caixa'!C14 -> 75207.393 | D14: ='Fluxo de Caixa'!D14 -> 53086.01 | E14: ='Fluxo de Caixa'!F14 -> 0 | F14: ='Fluxo de Caixa'!G14 -> 39404.597 | G14: =G13+F14 -> 8622.0262 | H14: =IF(G14>=0,"Sim","Não") -> Sim
A15: 10 | B15: ='Fluxo de Caixa'!B15 -> 209654 | C15: ='Fluxo de Caixa'!C15 -> 95573.588 | D15: ='Fluxo de Caixa'!D15 -> 63365.23 | E15: ='Fluxo de Caixa'!F15 -> 0 | F15: ='Fluxo de Caixa'!G15 -> 50715.182 | G15: =G14+F15 -> 59337.208 | H15: =IF(G15>=0,"Sim","Não") -> Sim
A16: 11 | B16: ='Fluxo de Caixa'!B16 -> 211610 | C16: ='Fluxo de Caixa'!C16 -> 91475.041 | D16: ='Fluxo de Caixa'!D16 -> 63844.45 | E16: ='Fluxo de Caixa'!F16 -> 0 | F16: ='Fluxo de Caixa'!G16 -> 56290.509 | G16: =G15+F16 -> 115627.72 | H16: =IF(G16>=0,"Sim","Não") -> Sim
A17: 12 | B17: ='Fluxo de Caixa'!B17 -> 255562 | C17: ='Fluxo de Caixa'!C17 -> 113561.27 | D17: ='Fluxo de Caixa'!D17 -> 74612.69 | E17: ='Fluxo de Caixa'!F17 -> 0 | F17: ='Fluxo de Caixa'!G17 -> 67388.045 | G17: =G16+F17 -> 183015.76 | H17: =IF(G17>=0,"Sim","Não") -> Sim
... A29: 24 | B29: ='Fluxo de Caixa'!B29 -> 648842 | C29: ='Fluxo de Caixa'!C29 -> 270968.48 | D29: ='Fluxo de Caixa'!D29 -> 170966.29 | E29: ='Fluxo de Caixa'!F29 -> 0 | F29: ='Fluxo de Caixa'!G29 -> 206907.23 | G29: =G28+F29 -> 1717572.2 | H29: =IF(G29>=0,"Sim","Não") -> Sim
A31: RESUMO
A32: Necessidade máxima de caixa (R$): | F32: =MAX(0,-MIN(G5:G29)) -> 118526.3 | G32: ← pior saldo: dinheiro que os sócios precisam ter
A33: Payback simples (1º período com saldo ≥ 0): | F33: =IFERROR(INDEX(A5:A29,MATCH("Sim",H5:H29,0)),"Não recupera") -> 9 | G33: ← 1º período com saldo acumulado ≥ 0

Sheet VPL e TIR
A1: ANÁLISE DE VIABILIDADE FINANCEIRA
A2: Preencha as duas células CINZAS abaixo. Todo o resto é calculado a partir da aba Fluxo de Caixa.
A4: 1. PARÂMETROS
A5: Taxa de desconto ANUAL (TMA): | B5: ='Premissas Precept'!B64 -> 0.24 | C5: Digite com o símbolo %: 15% (ou 0,15) para 15% ao ano. Exemplo usado: 15% a.a. (troque pela taxa do grupo).
A6: Os períodos da planilha são: | B6: Mensal | C6: Escolha na lista: Mensal ou Anual.
A7: Taxa de desconto por período: | B7: =IF(B6="Mensal",(1+B5)^(1/12)-1,B5) -> 0.018087582 | C7: Automático. Taxa mensal equivalente: (1 + taxa anual)^(1/12) − 1.
A9: 2. FLUXO DE CAIXA TRAZIDO A VALOR PRESENTE
A10: Período | B10: Fluxo de Caixa (R$) | C10: Fator de Desconto | D10: Valor Presente (R$) | E10: VP Acumulado (R$) | F10: Recuperado (descontado)?
A11: 0 | B11: ='Fluxo de Caixa'!G5 -> -102000 | C11: =1/(1+$B$7)^A11 -> 1 | D11: =B11*C11 -> -102000 | E11: =D11 -> -102000 | F11: =IF(E11>=0,"Sim","Não") -> Não
A12: 1 | B12: ='Fluxo de Caixa'!G6 -> -10779.9 | C12: =1/(1+$B$7)^A12 -> 0.98223377 | D12: =B12*C12 -> -10588.382 | E12: =E11+D12 -> -112588.38 | F12: =IF(E12>=0,"Sim","Não") -> Não
A13: 2 | B13: ='Fluxo de Caixa'!G7 -> -5746.4 | C13: =1/(1+$B$7)^A13 -> 0.96478317 | D13: =B13*C13 -> -5544.03 | E13: =E12+D13 -> -118132.41 | F13: =IF(E13>=0,"Sim","Não") -> Não
A14: 3 | B14: ='Fluxo de Caixa'!G8 -> 2100.5 | C14: =1/(1+$B$7)^A14 -> 0.94764261 | D14: =B14*C14 -> 1990.5233 | E14: =E13+D14 -> -116141.89 | F14: =IF(E14>=0,"Sim","Não") -> Não
A15: 4 | B15: ='Fluxo de Caixa'!G9 -> 791.43122 | C15: =1/(1+$B$7)^A15 -> 0.93080657 | D15: =B15*C15 -> 736.66937 | E15: =E14+D15 -> -115405.22 | F15: =IF(E15>=0,"Sim","Não") -> Não
A16: 5 | B16: ='Fluxo de Caixa'!G10 -> 8277.7589 | C16: =1/(1+$B$7)^A16 -> 0.91426964 | D16: =B16*C16 -> 7568.1037 | E16: =E15+D16 -> -107837.12 | F16: =IF(E16>=0,"Sim","Não") -> Não
A17: 6 | B17: ='Fluxo de Caixa'!G11 -> 19112.033 | C17: =1/(1+$B$7)^A17 -> 0.89802651 | D17: =B17*C17 -> 17163.113 | E17: =E16+D17 -> -90674.003 | F17: =IF(E17>=0,"Sim","Não") -> Não
A18: 7 | B18: ='Fluxo de Caixa'!G12 -> 23422.759 | C18: =1/(1+$B$7)^A18 -> 0.88207196 | D18: =B18*C18 -> 20660.559 | E18: =E17+D18 -> -70013.444 | F18: =IF(E18>=0,"Sim","Não") -> Não
A19: 8 | B19: ='Fluxo de Caixa'!G13 -> 34039.247 | C19: =1/(1+$B$7)^A19 -> 0.86640086 | D19: =B19*C19 -> 29491.633 | E19: =E18+D19 -> -40521.811 | F19: =IF(E19>=0,"Sim","Não") -> Não
A20: 9 | B20: ='Fluxo de Caixa'!G14 -> 39404.597 | C20: =1/(1+$B$7)^A20 -> 0.85100818 | D20: =B20*C20 -> 33533.635 | E20: =E19+D20 -> -6988.1767 | F20: =IF(E20>=0,"Sim","Não") -> Não
A21: 10 | B21: ='Fluxo de Caixa'!G15 -> 50715.182 | C21: =1/(1+$B$7)^A21 -> 0.83588897 | D21: =B21*C21 -> 42392.261 | E21: =E20+D21 -> 35404.085 | F21: =IF(E21>=0,"Sim","Não") -> Sim
A22: 11 | B22: ='Fluxo de Caixa'!G16 -> 56290.509 | C22: =1/(1+$B$7)^A22 -> 0.82103837 | D22: =B22*C22 -> 46216.668 | E22: =E21+D22 -> 81620.752 | F22: =IF(E22>=0,"Sim","Não") -> Sim
A23: 12 | B23: ='Fluxo de Caixa'!G17 -> 67388.045 | C23: =1/(1+$B$7)^A23 -> 0.80645161 | D23: =B23*C23 -> 54345.197 | E23: =E22+D23 -> 135965.95 | F23: =IF(E23>=0,"Sim","Não") -> Sim
... A35: 24 | B35: ='Fluxo de Caixa'!G29 -> 206907.23 | C35: =1/(1+$B$7)^A35 -> 0.6503642 | D35: =B35*C35 -> 134565.05 | E35: =E34+D35 -> 1220849.3 | F35: =IF(E35>=0,"Sim","Não") -> Sim
A37: 3. RESULTADOS
A38: Valor Presente Líquido (VPL): | B38: =SUM(D11:D35) -> 1220849.3 | C38: =IF(B38>0,"VIÁVEL: o projeto gera mais do que a taxa exigida",IF(B38<0,"INVIÁVEL: o projeto rende menos que a taxa exigida","EQUILÍBRIO: rende exatamente a taxa exigida")) -> VIÁVEL: o projeto gera mais do que a taxa exigida
A39: TIR por período: | B39: =IFERROR(IRR(B11:B35),"Não calculável") -> 0.19625981 | C39: =IF(ISNUMBER(B39),IF(B39>B7,"VIÁVEL: TIR maior que a taxa de desconto","INVIÁVEL: TIR menor ou igual à taxa de desconto"),"Sem TIR: o fluxo precisa ter valores negativos E positivos") -> VIÁVEL: TIR maior que a taxa de desconto
A40: TIR equivalente ao ano: | B40: =IF(ISNUMBER(B39),IF(B6="Mensal",(1+B39)^12-1,B39),"Não calculável") -> 7.5882793 | C40: ="Compare com a taxa anual de "&ROUND(B5*100,2)&"%" -> Compare com a taxa anual de 24%
A41: Investimento inicial (período 0): | B41: ='Fluxo de Caixa'!F5 -> 102000 | C41: =IF(B41=0,"Atenção: informe o investimento no período 0 da aba Fluxo de Caixa","")
A42: VPL em % do investimento inicial: | B42: =IF(B41=0,"-",B38/B41) -> 11.969111 | C42: ="Para cada R$ 100 de investimento inicial, o projeto gera R$ "&IF(ISNUMBER(B42),ROUND(B42*100,2),"-")&" de VPL acima da taxa exigida" -> Para cada R$ 100 de investimento inicial, o projeto gera R$ 1196.91 de VPL acima da taxa exigida
A43: Payback simples (1º período com saldo ≥ 0): | B43: ='Necessidade de Caixa e Payback'!F33 -> 9 | C43: ="Período em que o saldo acumulado (sem descontar) fica positivo" -> Período em que o saldo acumulado (sem descontar) fica positivo
A44: Payback descontado (1º período com VP acum. ≥ 0): | B44: =IFERROR(INDEX(A11:A35,MATCH("Sim",F11:F35,0)),"Não recupera") -> 10 | C44: ="Período em que o VP acumulado fica positivo" -> Período em que o VP acumulado fica positivo
A45: Necessidade máxima de caixa: | B45: ='Necessidade de Caixa e Payback'!F32 -> 118526.3 | C45: ="Dinheiro que os sócios precisam ter para cobrir o pior momento" -> Dinheiro que os sócios precisam ter para cobrir o pior momento
A47: 4. COMO LER OS RESULTADOS
A48: • VPL > 0 → viável: o projeto devolve o investimento, paga a taxa exigida e ainda gera o valor mostrado (em R$ de hoje).
A49: • VPL < 0 → inviável nas premissas atuais: revise preço, volume, custos ou investimento e teste novos cenários.
A50: • TIR > taxa de desconto → viável. VPL e TIR normalmente apontam a mesma decisão; se divergirem, prefira o VPL.
A51: • Cuidado com a TIR quando o fluxo muda de sinal mais de uma vez (ex.: novo investimento no meio do projeto): ela pode ser enganosa. Nesse caso, decida pelo VPL.
A52: • Payback: quanto menor, mais rápido o dinheiro volta e menor o risco. O descontado é o mais rigoroso.
A53: • Necessidade máxima de caixa: os sócios precisam ter esse valor disponível (investimento + prejuízos iniciais).
