Workbook

Sheet Instruções
A1: PLANILHA DE ANÁLISE FINANCEIRA – VPL, TIR E PAYBACK
A2: Viabilidade de projetos empreendedores – Projetos Empreendedores, Mackenzie
A4: PASSO A PASSO
A5: 1. Aba Fluxo de Caixa: preencha SÓ as células CINZAS (vendas, despesas e investimentos de cada período).
A6: 2. Período 0 = hoje, antes de começar a vender. Coloque ali o investimento inicial (equipamentos, reforma, abertura da empresa etc.).
A7: 3. Períodos 1 a 24 = meses (ou anos) de operação. Se o projeto durar menos, deixe os períodos restantes em branco.
A8: 4. Aba VPL e TIR: informe a taxa de desconto ANUAL e se os períodos são meses ou anos. A planilha converte a taxa sozinha.
A9: 5. Leia os resultados (VPL, TIR, payback) e a frase de decisão. Células AZUIS são automáticas e estão protegidas.
A11: LEGENDA DE CORES
A12: Cinza = você preenche | Azul = cálculo automático | Amarelo = resultado principal | Verde/vermelho = viável/inviável
A13: Passe o mouse sobre os títulos das colunas para ver a explicação de cada uma.
A15: GLOSSÁRIO
... A32: • Os valores que já vêm na planilha são apenas EXEMPLO. Substitua pelos dados do seu projeto.

Sheet Fluxo de Caixa
A1: FLUXO DE CAIXA DETALHADO
A2: Preencha as células CINZAS. As AZUIS são calculadas. Período 0 = investimento inicial; períodos 1 a 24 = operação.
A4: Período | B4: Vendas Brutas (R$) | C4: Despesas Variáveis (R$) | D4: Despesas Fixas (R$) | E4: Resultado Operacional (R$) | F4: Investimentos (R$) | G4: Fluxo de Caixa Líquido (R$)
A5: 0 | B5: 0 | C5: 0 | D5: 0 | E5: =B5-C5-D5 -> 0 | F5: 102000 | G5: =E5-F5 -> -102000
A6: 1 | B6: 5988 | C6: 4767.9 | D6: 12000 | E6: =B6-C6-D6 -> -10779.9 | F6: 0 | G6: =E6-F6 -> -10779.9
A7: 2 | B7: 15968 | C7: 9714.4 | D7: 12000 | E7: =B7-C7-D7 -> -5746.4 | F7: 0 | G7: =E7-F7 -> -5746.4
A8: 3 | B8: 29940 | C8: 15839.5 | D8: 12000 | E8: =B8-C8-D8 -> 2100.5 | F8: 0 | G8: =E8-F8 -> 2100.5
A9: 4 | B9: 57901 | C9: 30923.82 | D9: 26185.75 | E9: =B9-C9-D9 -> 791.43 | F9: 0 | G9: =E9-F9 -> 791.43
A10: 5 | B10: 77861 | C10: 38507.3 | D10: 31075.95 | E10: =B10-C10-D10 -> 8277.75 | F10: 0 | G10: =E10-F10 -> 8277.75
A11: 6 | B11: 125822 | C11: 63883.58 | D11: 42826.39 | E11: =B11-C11-D11 -> 19112.03 | F11: 0 | G11: =E11-F11 -> 19112.03
A12: 7 | B12: 117781 | C12: 53501.9 | D12: 40856.35 | E12: =B12-C12-D12 -> 23422.75 | F12: 0 | G12: =E12-F12 -> 23422.75
A13: 8 | B13: 165742 | C13: 79095.96 | D13: 52606.79 | E13: =B13-C13-D13 -> 34039.25 | F13: 0 | G13: =E13-F13 -> 34039.25
A14: 9 | B14: 167698 | C14: 75207.39 | D14: 53086.01 | E14: =B14-C14-D14 -> 39404.6 | F14: 0 | G14: =E14-F14 -> 39404.6
A15: 10 | B15: 209654 | C15: 95573.59 | D15: 63365.23 | E15: =B15-C15-D15 -> 50715.18 | F15: 0 | G15: =E15-F15 -> 50715.18
A16: 11 | B16: 211610 | C16: 91475.04 | D16: 63844.45 | E16: =B16-C16-D16 -> 56290.51 | F16: 0 | G16: =E16-F16 -> 56290.51
... A29: 24 | B29: 648842 | C29: 270968.48 | D29: 170966.29 | E29: =B29-C29-D29 -> 206907.23 | F29: 0 | G29: =E29-F29 -> 206907.23
A30: TOTAL | B30: =SUM(B5:B29) -> 6989956 | C30: =SUM(C5:C29) -> 3182559.1 | D30: =SUM(D5:D29) -> 1987824.8 | E30: =SUM(E5:E29) -> 1819572.2 | F30: =SUM(F5:F29) -> 102000 | G30: =SUM(G5:G29) -> 1717572.2
A32: Valores atuais são EXEMPLO (investimento de R$ 50.000 e lucro operacional de R$ 4.000/mês). Substitua pelos dados do seu projeto.

Sheet Necessidade de Caixa e Payback
A1: SALDO ACUMULADO, NECESSIDADE DE CAIXA E PAYBACK
A2: Aba 100% automática. Mostra quanto dinheiro o projeto acumula (ou consome) ao longo do tempo.
A4: Período | B4: Vendas Brutas (R$) | C4: Despesas Variáveis (R$) | D4: Despesas Fixas (R$) | E4: Investimentos (R$) | F4: Fluxo de Caixa Líquido (R$) | G4: Saldo Acumulado (R$) | H4: Investimento recuperado?
A5: 0 | B5: ='Fluxo de Caixa'!B5 -> 0 | C5: ='Fluxo de Caixa'!C5 -> 0 | D5: ='Fluxo de Caixa'!D5 -> 0 | E5: ='Fluxo de Caixa'!F5 -> 102000 | F5: ='Fluxo de Caixa'!G5 -> -102000 | G5: =F5 -> -102000 | H5: =IF(G5>=0,"Sim","Não") -> Não
A6: 1 | B6: ='Fluxo de Caixa'!B6 -> 5988 | C6: ='Fluxo de Caixa'!C6 -> 4767.9 | D6: ='Fluxo de Caixa'!D6 -> 12000 | E6: ='Fluxo de Caixa'!F6 -> 0 | F6: ='Fluxo de Caixa'!G6 -> -10779.9 | G6: =G5+F6 -> -112779.9 | H6: =IF(G6>=0,"Sim","Não") -> Não
A7: 2 | B7: ='Fluxo de Caixa'!B7 -> 15968 | C7: ='Fluxo de Caixa'!C7 -> 9714.4 | D7: ='Fluxo de Caixa'!D7 -> 12000 | E7: ='Fluxo de Caixa'!F7 -> 0 | F7: ='Fluxo de Caixa'!G7 -> -5746.4 | G7: =G6+F7 -> -118526.3 | H7: =IF(G7>=0,"Sim","Não") -> Não
A8: 3 | B8: ='Fluxo de Caixa'!B8 -> 29940 | C8: ='Fluxo de Caixa'!C8 -> 15839.5 | D8: ='Fluxo de Caixa'!D8 -> 12000 | E8: ='Fluxo de Caixa'!F8 -> 0 | F8: ='Fluxo de Caixa'!G8 -> 2100.5 | G8: =G7+F8 -> -116425.8 | H8: =IF(G8>=0,"Sim","Não") -> Não
A9: 4 | B9: ='Fluxo de Caixa'!B9 -> 57901 | C9: ='Fluxo de Caixa'!C9 -> 30923.82 | D9: ='Fluxo de Caixa'!D9 -> 26185.75 | E9: ='Fluxo de Caixa'!F9 -> 0 | F9: ='Fluxo de Caixa'!G9 -> 791.43 | G9: =G8+F9 -> -115634.37 | H9: =IF(G9>=0,"Sim","Não") -> Não
A10: 5 | B10: ='Fluxo de Caixa'!B10 -> 77861 | C10: ='Fluxo de Caixa'!C10 -> 38507.3 | D10: ='Fluxo de Caixa'!D10 -> 31075.95 | E10: ='Fluxo de Caixa'!F10 -> 0 | F10: ='Fluxo de Caixa'!G10 -> 8277.75 | G10: =G9+F10 -> -107356.62 | H10: =IF(G10>=0,"Sim","Não") -> Não
A11: 6 | B11: ='Fluxo de Caixa'!B11 -> 125822 | C11: ='Fluxo de Caixa'!C11 -> 63883.58 | D11: ='Fluxo de Caixa'!D11 -> 42826.39 | E11: ='Fluxo de Caixa'!F11 -> 0 | F11: ='Fluxo de Caixa'!G11 -> 19112.03 | G11: =G10+F11 -> -88244.59 | H11: =IF(G11>=0,"Sim","Não") -> Não
A12: 7 | B12: ='Fluxo de Caixa'!B12 -> 117781 | C12: ='Fluxo de Caixa'!C12 -> 53501.9 | D12: ='Fluxo de Caixa'!D12 -> 40856.35 | E12: ='Fluxo de Caixa'!F12 -> 0 | F12: ='Fluxo de Caixa'!G12 -> 23422.75 | G12: =G11+F12 -> -64821.84 | H12: =IF(G12>=0,"Sim","Não") -> Não
A13: 8 | B13: ='Fluxo de Caixa'!B13 -> 165742 | C13: ='Fluxo de Caixa'!C13 -> 79095.96 | D13: ='Fluxo de Caixa'!D13 -> 52606.79 | E13: ='Fluxo de Caixa'!F13 -> 0 | F13: ='Fluxo de Caixa'!G13 -> 34039.25 | G13: =G12+F13 -> -30782.59 | H13: =IF(G13>=0,"Sim","Não") -> Não
A14: 9 | B14: ='Fluxo de Caixa'!B14 -> 167698 | C14: ='Fluxo de Caixa'!C14 -> 75207.39 | D14: ='Fluxo de Caixa'!D14 -> 53086.01 | E14: ='Fluxo de Caixa'!F14 -> 0 | F14: ='Fluxo de Caixa'!G14 -> 39404.6 | G14: =G13+F14 -> 8622.01 | H14: =IF(G14>=0,"Sim","Não") -> Sim
A15: 10 | B15: ='Fluxo de Caixa'!B15 -> 209654 | C15: ='Fluxo de Caixa'!C15 -> 95573.59 | D15: ='Fluxo de Caixa'!D15 -> 63365.23 | E15: ='Fluxo de Caixa'!F15 -> 0 | F15: ='Fluxo de Caixa'!G15 -> 50715.18 | G15: =G14+F15 -> 59337.19 | H15: =IF(G15>=0,"Sim","Não") -> Sim
A16: 11 | B16: ='Fluxo de Caixa'!B16 -> 211610 | C16: ='Fluxo de Caixa'!C16 -> 91475.04 | D16: ='Fluxo de Caixa'!D16 -> 63844.45 | E16: ='Fluxo de Caixa'!F16 -> 0 | F16: ='Fluxo de Caixa'!G16 -> 56290.51 | G16: =G15+F16 -> 115627.7 | H16: =IF(G16>=0,"Sim","Não") -> Sim
A17: 12 | B17: ='Fluxo de Caixa'!B17 -> 255562 | C17: ='Fluxo de Caixa'!C17 -> 113561.27 | D17: ='Fluxo de Caixa'!D17 -> 74612.69 | E17: ='Fluxo de Caixa'!F17 -> 0 | F17: ='Fluxo de Caixa'!G17 -> 67388.04 | G17: =G16+F17 -> 183015.74 | H17: =IF(G17>=0,"Sim","Não") -> Sim
... A29: 24 | B29: ='Fluxo de Caixa'!B29 -> 648842 | C29: ='Fluxo de Caixa'!C29 -> 270968.48 | D29: ='Fluxo de Caixa'!D29 -> 170966.29 | E29: ='Fluxo de Caixa'!F29 -> 0 | F29: ='Fluxo de Caixa'!G29 -> 206907.23 | G29: =G28+F29 -> 1717572.2 | H29: =IF(G29>=0,"Sim","Não") -> Sim
A31: RESUMO
A32: Necessidade máxima de caixa (R$): | F32: =MAX(0,-MIN(G5:G29)) -> 118526.3 | G32: ← pior saldo: dinheiro que os sócios precisam ter
A33: Payback simples (1º período com saldo ≥ 0): | F33: =IFERROR(INDEX(A5:A29,MATCH("Sim",H5:H29,0)),"Não recupera") -> 9 | G33: ← 1º período com saldo acumulado ≥ 0

Sheet VPL e TIR
A1: ANÁLISE DE VIABILIDADE FINANCEIRA
A2: Preencha as duas células CINZAS abaixo. Todo o resto é calculado a partir da aba Fluxo de Caixa.
A4: 1. PARÂMETROS
A5: Taxa de desconto ANUAL (TMA): | B5: 0.24 | C5: Digite com o símbolo %: 15% (ou 0,15) para 15% ao ano. Exemplo usado: 15% a.a. (troque pela taxa do grupo).
A6: Os períodos da planilha são: | B6: Mensal | C6: Escolha na lista: Mensal ou Anual.
A7: Taxa de desconto por período: | B7: =IF(B6="Mensal",(1+B5)^(1/12)-1,B5) -> 0.018087582 | C7: Automático. Taxa mensal equivalente: (1 + taxa anual)^(1/12) − 1.
A9: 2. FLUXO DE CAIXA TRAZIDO A VALOR PRESENTE
A10: Período | B10: Fluxo de Caixa (R$) | C10: Fator de Desconto | D10: Valor Presente (R$) | E10: VP Acumulado (R$) | F10: Recuperado (descontado)?
A11: 0 | B11: ='Fluxo de Caixa'!G5 -> -102000 | C11: =1/(1+$B$7)^A11 -> 1 | D11: =B11*C11 -> -102000 | E11: =D11 -> -102000 | F11: =IF(E11>=0,"Sim","Não") -> Não
A12: 1 | B12: ='Fluxo de Caixa'!G6 -> -10779.9 | C12: =1/(1+$B$7)^A12 -> 0.98223377 | D12: =B12*C12 -> -10588.382 | E12: =E11+D12 -> -112588.38 | F12: =IF(E12>=0,"Sim","Não") -> Não
A13: 2 | B13: ='Fluxo de Caixa'!G7 -> -5746.4 | C13: =1/(1+$B$7)^A13 -> 0.96478317 | D13: =B13*C13 -> -5544.03 | E13: =E12+D13 -> -118132.41 | F13: =IF(E13>=0,"Sim","Não") -> Não
A14: 3 | B14: ='Fluxo de Caixa'!G8 -> 2100.5 | C14: =1/(1+$B$7)^A14 -> 0.94764261 | D14: =B14*C14 -> 1990.5233 | E14: =E13+D14 -> -116141.89 | F14: =IF(E14>=0,"Sim","Não") -> Não
A15: 4 | B15: ='Fluxo de Caixa'!G9 -> 791.43 | C15: =1/(1+$B$7)^A15 -> 0.93080657 | D15: =B15*C15 -> 736.66824 | E15: =E14+D15 -> -115405.22 | F15: =IF(E15>=0,"Sim","Não") -> Não
A16: 5 | B16: ='Fluxo de Caixa'!G10 -> 8277.75 | C16: =1/(1+$B$7)^A16 -> 0.91426964 | D16: =B16*C16 -> 7568.0955 | E16: =E15+D16 -> -107837.12 | F16: =IF(E16>=0,"Sim","Não") -> Não
A17: 6 | B17: ='Fluxo de Caixa'!G11 -> 19112.03 | C17: =1/(1+$B$7)^A17 -> 0.89802651 | D17: =B17*C17 -> 17163.11 | E17: =E16+D17 -> -90674.015 | F17: =IF(E17>=0,"Sim","Não") -> Não
A18: 7 | B18: ='Fluxo de Caixa'!G12 -> 23422.75 | C18: =1/(1+$B$7)^A18 -> 0.88207196 | D18: =B18*C18 -> 20660.551 | E18: =E17+D18 -> -70013.464 | F18: =IF(E18>=0,"Sim","Não") -> Não
A19: 8 | B19: ='Fluxo de Caixa'!G13 -> 34039.25 | C19: =1/(1+$B$7)^A19 -> 0.86640086 | D19: =B19*C19 -> 29491.636 | E19: =E18+D19 -> -40521.829 | F19: =IF(E19>=0,"Sim","Não") -> Não
A20: 9 | B20: ='Fluxo de Caixa'!G14 -> 39404.6 | C20: =1/(1+$B$7)^A20 -> 0.85100818 | D20: =B20*C20 -> 33533.637 | E20: =E19+D20 -> -6988.1915 | F20: =IF(E20>=0,"Sim","Não") -> Não
A21: 10 | B21: ='Fluxo de Caixa'!G15 -> 50715.18 | C21: =1/(1+$B$7)^A21 -> 0.83588897 | D21: =B21*C21 -> 42392.26 | E21: =E20+D21 -> 35404.068 | F21: =IF(E21>=0,"Sim","Não") -> Sim
A22: 11 | B22: ='Fluxo de Caixa'!G16 -> 56290.51 | C22: =1/(1+$B$7)^A22 -> 0.82103837 | D22: =B22*C22 -> 46216.669 | E22: =E21+D22 -> 81620.737 | F22: =IF(E22>=0,"Sim","Não") -> Sim
A23: 12 | B23: ='Fluxo de Caixa'!G17 -> 67388.04 | C23: =1/(1+$B$7)^A23 -> 0.80645161 | D23: =B23*C23 -> 54345.194 | E23: =E22+D23 -> 135965.93 | F23: =IF(E23>=0,"Sim","Não") -> Sim
... A35: 24 | B35: ='Fluxo de Caixa'!G29 -> 206907.23 | C35: =1/(1+$B$7)^A35 -> 0.6503642 | D35: =B35*C35 -> 134565.06 | E35: =E34+D35 -> 1220849.2 | F35: =IF(E35>=0,"Sim","Não") -> Sim
A37: 3. RESULTADOS
A38: Valor Presente Líquido (VPL): | B38: =SUM(D11:D35) -> 1220849.2 | C38: =IF(B38>0,"VIÁVEL: o projeto gera mais do que a taxa exigida",IF(B38<0,"INVIÁVEL: o projeto rende menos que a taxa exigida","EQUILÍBRIO: rende exatamente a taxa exigida")) -> VIÁVEL: o projeto gera mais do que a taxa exigida
A39: TIR por período: | B39: =IFERROR(IRR(B11:B35),"Não calculável") -> 0.1962598 | C39: =IF(ISNUMBER(B39),IF(B39>B7,"VIÁVEL: TIR maior que a taxa de desconto","INVIÁVEL: TIR menor ou igual à taxa de desconto"),"Sem TIR: o fluxo precisa ter valores negativos E positivos") -> VIÁVEL: TIR maior que a taxa de desconto
A40: TIR equivalente ao ano: | B40: =IF(ISNUMBER(B39),IF(B6="Mensal",(1+B39)^12-1,B39),"Não calculável") -> 7.5882786 | C40: ="Compare com a taxa anual de "&ROUND(B5*100,2)&"%" -> Compare com a taxa anual de 24%
A41: Investimento inicial (período 0): | B41: ='Fluxo de Caixa'!F5 -> 102000 | C41: =IF(B41=0,"Atenção: informe o investimento no período 0 da aba Fluxo de Caixa","")
A42: VPL em % do investimento inicial: | B42: =IF(B41=0,"-",B38/B41) -> 11.96911 | C42: ="Para cada R$ 100 de investimento inicial, o projeto gera R$ "&IF(ISNUMBER(B42),ROUND(B42*100,2),"-")&" de VPL acima da taxa exigida" -> Para cada R$ 100 de investimento inicial, o projeto gera R$ 1196.91 de VPL acima da taxa exigida
A43: Payback simples (1º período com saldo ≥ 0): | B43: ='Necessidade de Caixa e Payback'!F33 -> 9 | C43: ="Período em que o saldo acumulado (sem descontar) fica positivo" -> Período em que o saldo acumulado (sem descontar) fica positivo
A44: Payback descontado (1º período com VP acum. ≥ 0): | B44: =IFERROR(INDEX(A11:A35,MATCH("Sim",F11:F35,0)),"Não recupera") -> 10 | C44: ="Período em que o VP acumulado fica positivo" -> Período em que o VP acumulado fica positivo
A45: Necessidade máxima de caixa: | B45: ='Necessidade de Caixa e Payback'!F32 -> 118526.3 | C45: ="Dinheiro que os sócios precisam ter para cobrir o pior momento" -> Dinheiro que os sócios precisam ter para cobrir o pior momento
A47: 4. COMO LER OS RESULTADOS
A48: • VPL > 0 → viável: o projeto devolve o investimento, paga a taxa exigida e ainda gera o valor mostrado (em R$ de hoje).
A49: • VPL < 0 → inviável nas premissas atuais: revise preço, volume, custos ou investimento e teste novos cenários.
A50: • TIR > taxa de desconto → viável. VPL e TIR normalmente apontam a mesma decisão; se divergirem, prefira o VPL.
A51: • Cuidado com a TIR quando o fluxo muda de sinal mais de uma vez (ex.: novo investimento no meio do projeto): ela pode ser enganosa. Nesse caso, decida pelo VPL.
A52: • Payback: quanto menor, mais rápido o dinheiro volta e menor o risco. O descontado é o mais rigoroso.
A53: • Necessidade máxima de caixa: os sócios precisam ter esse valor disponível (investimento + prejuízos iniciais).
